[
    {
        "Subreddit": "r/ShopeePH",
        "Community Category": "Marketplace and Deals",
        "Member Count": "44948"
    },
    {
        "Subreddit": "r/masteruwuoficial",
        "Community Category": "Mature Themes and Adult Content",
        "Member Count": "44941"
    },
    {
        "Subreddit": "r/OceanGateTitan",
        "Community Category": "World News",
        "Member Count": "44932"
    },
    {
        "Subreddit": "r/TwerkersInternational",
        "Community Category": "Mature Themes and Adult Content",
        "Member Count": "44930"
    },
    {
        "Subreddit": "r/pothos",
        "Community Category": "Home and Garden",
        "Member Count": "44916"
    },
    {
        "Subreddit": "r/IDONTGIVEASWAG",
        "Community Category": "Internet Culture and Memes",
        "Member Count": "44885"
    },
    {
        "Subreddit": "r/CivPolitics",
        "Community Category": "Internet Culture and Memes",
        "Member Count": "44872"
    },
    {
        "Subreddit": "r/diydrones",
        "Community Category": "Technology",
        "Member Count": "44863"
    },
    {
        "Subreddit": "r/NYCbike",
        "Community Category": "Place",
        "Member Count": "44858"
    },
    {
        "Subreddit": "r/Amiibomb",
        "Community Category": "Gaming",
        "Member Count": "44843"
    },
    {
        "Subreddit": "r/TitansTV",
        "Community Category": "Television",
        "Member Count": "44841"
    },
    {
        "Subreddit": "r/okbuddygenshin",
        "Community Category": "Gaming",
        "Member Count": "44836"
    },
    {
        "Subreddit": "r/Pathfinder",
        "Community Category": "Tabletop Games",
        "Member Count": "44815"
    },
    {
        "Subreddit": "r/pixelography",
        "Community Category": "Art",
        "Member Count": "44805"
    },
    {
        "Subreddit": "r/formcheck",
        "Community Category": "Fitness and Nutrition",
        "Member Count": "44791"
    },
    {
        "Subreddit": "r/Digibyte",
        "Community Category": "Crypto",
        "Member Count": "44778"
    },
    {
        "Subreddit": "r/lightingdesign",
        "Community Category": "Technology",
        "Member Count": "44775"
    },
    {
        "Subreddit": "r/OkayBuddyLiterallyMe",
        "Community Category": "Internet Culture and Memes",
        "Member Count": "44775"
    },
    {
        "Subreddit": "r/carcamping",
        "Community Category": "Travel",
        "Member Count": "44763"
    },
    {
        "Subreddit": "r/676",
        "Community Category": "Funny/Humor",
        "Member Count": "44748"
    },
    {
        "Subreddit": "r/MoDaoZuShi",
        "Community Category": "Anime",
        "Member Count": "44748"
    },
    {
        "Subreddit": "r/brittanydawnsnark",
        "Community Category": "Celebrity",
        "Member Count": "44735"
    },
    {
        "Subreddit": "r/GarandThumb",
        "Community Category": "Podcasts and Streamers",
        "Member Count": "44733"
    },
    {
        "Subreddit": "r/Kerddit",
        "Community Category": "Gaming",
        "Member Count": "44730"
    },
    {
        "Subreddit": "r/termux",
        "Community Category": "Programming",
        "Member Count": "44728"
    },
    {
        "Subreddit": "r/SorryLag",
        "Community Category": "Podcasts and Streamers",
        "Member Count": "44718"
    },
    {
        "Subreddit": "r/dumbphones",
        "Community Category": "Technology",
        "Member Count": "44708"
    },
    {
        "Subreddit": "r/media_criticism",
        "Community Category": "World News",
        "Member Count": "44697"
    },
    {
        "Subreddit": "r/braces",
        "Community Category": "Medical and Mental Health",
        "Member Count": "44696"
    },
    {
        "Subreddit": "r/CellToSingularity",
        "Community Category": "Gaming",
        "Member Count": "44693"
    },
    {
        "Subreddit": "r/PetAfterVet",
        "Community Category": "Animals and Pets",
        "Member Count": "44678"
    },
    {
        "Subreddit": "r/blankies",
        "Community Category": "Podcasts and Streamers",
        "Member Count": "44675"
    },
    {
        "Subreddit": "r/TotalKalesh",
        "Community Category": "Mature Themes and Adult Content",
        "Member Count": "44644"
    },
    {
        "Subreddit": "r/FrutigerAero",
        "Community Category": "Art",
        "Member Count": "44633"
    },
    {
        "Subreddit": "r/OldSchoolCoolMusic",
        "Community Category": "Music",
        "Member Count": "44629"
    },
    {
        "Subreddit": "r/octopus",
        "Community Category": "Animals and Pets",
        "Member Count": "44625"
    },
    {
        "Subreddit": "r/AsianTikTokGirls",
        "Community Category": "Mature Themes and Adult Content",
        "Member Count": "44624"
    },
    {
        "Subreddit": "r/appliancerepair",
        "Community Category": "Crafts and DIY",
        "Member Count": "44617"
    },
    {
        "Subreddit": "r/mobilerepair",
        "Community Category": "Crafts and DIY",
        "Member Count": "44615"
    },
    {
        "Subreddit": "r/AXELNetwork",
        "Community Category": "Crypto",
        "Member Count": "44613"
    },
    {
        "Subreddit": "r/foodsafety",
        "Community Category": "Food and Drink",
        "Member Count": "44613"
    },
    {
        "Subreddit": "r/IELTS",
        "Community Category": "Learning and Education",
        "Member Count": "44612"
    },
    {
        "Subreddit": "r/firebrigade",
        "Community Category": "Anime",
        "Member Count": "44607"
    },
    {
        "Subreddit": "r/budget",
        "Community Category": "Business, Economics, and Finance",
        "Member Count": "44596"
    },
    {
        "Subreddit": "r/Jamaica",
        "Community Category": "Place",
        "Member Count": "44593"
    },
    {
        "Subreddit": "r/offset",
        "Community Category": "Music",
        "Member Count": "44591"
    },
    {
        "Subreddit": "r/DIYBeauty",
        "Community Category": "Beauty and Makeup",
        "Member Count": "44584"
    },
    {
        "Subreddit": "r/DrawingPrompts",
        "Community Category": "Art",
        "Member Count": "44578"
    },
    {
        "Subreddit": "r/IndianBeautyDeals",
        "Community Category": "Beauty and Makeup",
        "Member Count": "44574"
    },
    {
        "Subreddit": "r/Cd_collectors",
        "Community Category": "Music",
        "Member Count": "44573"
    },
    {
        "Subreddit": "r/fresno",
        "Community Category": "Place",
        "Member Count": "44571"
    },
    {
        "Subreddit": "r/xTrill",
        "Community Category": "Music",
        "Member Count": "44570"
    },
    {
        "Subreddit": "r/dontyouknowimtonyhawk",
        "Community Category": "Celebrity",
        "Member Count": "44556"
    },
    {
        "Subreddit": "r/Tsunderes",
        "Community Category": "Anime",
        "Member Count": "44555"
    },
    {
        "Subreddit": "r/NewToEMS",
        "Community Category": "Careers",
        "Member Count": "44536"
    },
    {
        "Subreddit": "r/TheTempleOfOchako",
        "Community Category": "Anime",
        "Member Count": "44532"
    },
    {
        "Subreddit": "r/ToyotaTundra",
        "Community Category": "Cars and Motor Vehicles",
        "Member Count": "44527"
    },
    {
        "Subreddit": "r/grateful_dead",
        "Community Category": "Music",
        "Member Count": "44526"
    },
    {
        "Subreddit": "r/sharktank",
        "Community Category": "Television",
        "Member Count": "44521"
    },
    {
        "Subreddit": "r/BeeSwarmSimulator",
        "Community Category": "Gaming",
        "Member Count": "44507"
    },
    {
        "Subreddit": "r/babies",
        "Community Category": "Family and Relationships",
        "Member Count": "44495"
    },
    {
        "Subreddit": "r/Pigifs",
        "Community Category": "Animals and Pets",
        "Member Count": "44493"
    },
    {
        "Subreddit": "r/GameDevelopersOfIndia",
        "Community Category": "Programming",
        "Member Count": "44489"
    },
    {
        "Subreddit": "r/Fansly_Advice",
        "Community Category": "Mature Themes and Adult Content",
        "Member Count": "44480"
    },
    {
        "Subreddit": "r/Militariacollecting",
        "Community Category": "History",
        "Member Count": "44461"
    },
    {
        "Subreddit": "r/Hoboken",
        "Community Category": "Place",
        "Member Count": "44456"
    },
    {
        "Subreddit": "r/WomenSoccerLegs",
        "Community Category": "Sports",
        "Member Count": "44446"
    },
    {
        "Subreddit": "r/kpopforsale",
        "Community Category": "Music",
        "Member Count": "44437"
    },
    {
        "Subreddit": "r/catssittingdown",
        "Community Category": "Animals and Pets",
        "Member Count": "44428"
    },
    {
        "Subreddit": "r/catastrophicsuccess",
        "Community Category": "Funny/Humor",
        "Member Count": "44416"
    },
    {
        "Subreddit": "r/Lorcana",
        "Community Category": "Tabletop Games",
        "Member Count": "44416"
    },
    {
        "Subreddit": "r/nuclear",
        "Community Category": "Science",
        "Member Count": "44402"
    },
    {
        "Subreddit": "r/interactivebrokers",
        "Community Category": "Business, Economics, and Finance",
        "Member Count": "44401"
    },
    {
        "Subreddit": "r/wildhearthstone",
        "Community Category": "Gaming",
        "Member Count": "44386"
    },
    {
        "Subreddit": "r/theviralthings",
        "Community Category": "Internet Culture and Memes",
        "Member Count": "44374"
    },
    {
        "Subreddit": "r/GarminWatches",
        "Community Category": "Technology",
        "Member Count": "44360"
    },
    {
        "Subreddit": "r/ManifestNBC",
        "Community Category": "Television",
        "Member Count": "44349"
    },
    {
        "Subreddit": "r/Ninjago",
        "Community Category": "Television",
        "Member Count": "44330"
    },
    {
        "Subreddit": "r/codingbootcamp",
        "Community Category": "Programming",
        "Member Count": "44324"
    },
    {
        "Subreddit": "r/WatchAnimalsDieInside",
        "Community Category": "Animals and Pets",
        "Member Count": "44324"
    },
    {
        "Subreddit": "r/AccidentalKubrick",
        "Community Category": "Movies",
        "Member Count": "44320"
    },
    {
        "Subreddit": "r/CreedThoughts",
        "Community Category": "Television",
        "Member Count": "44319"
    },
    {
        "Subreddit": "r/SmilingFriends",
        "Community Category": "Television",
        "Member Count": "44318"
    },
    {
        "Subreddit": "r/FitBlackGirls",
        "Community Category": "Mature Themes and Adult Content",
        "Member Count": "44313"
    },
    {
        "Subreddit": "r/Flooring",
        "Community Category": "Home and Garden",
        "Member Count": "44312"
    },
    {
        "Subreddit": "r/zilliqa",
        "Community Category": "Crypto",
        "Member Count": "44301"
    },
    {
        "Subreddit": "r/beach",
        "Community Category": "Outdoors and Nature",
        "Member Count": "44296"
    },
    {
        "Subreddit": "r/90DayFianceFans",
        "Community Category": "Television",
        "Member Count": "44295"
    },
    {
        "Subreddit": "r/prius",
        "Community Category": "Cars and Motor Vehicles",
        "Member Count": "44269"
    },
    {
        "Subreddit": "r/Yoimiya_Mains",
        "Community Category": "Gaming",
        "Member Count": "44262"
    },
    {
        "Subreddit": "r/AnimeNoises",
        "Community Category": "Anime",
        "Member Count": "44256"
    },
    {
        "Subreddit": "r/McMaster",
        "Community Category": "Learning and Education",
        "Member Count": "44256"
    },
    {
        "Subreddit": "r/DermatologyQuestions",
        "Community Category": "Medical and Mental Health",
        "Member Count": "44249"
    },
    {
        "Subreddit": "r/CapitalismSux",
        "Community Category": "Politics",
        "Member Count": "44247"
    },
    {
        "Subreddit": "r/nonprofit",
        "Community Category": "Careers",
        "Member Count": "44239"
    },
    {
        "Subreddit": "r/geologycareers",
        "Community Category": "Careers",
        "Member Count": "44231"
    },
    {
        "Subreddit": "r/350z",
        "Community Category": "Cars and Motor Vehicles",
        "Member Count": "44225"
    },
    {
        "Subreddit": "r/deusasbrazil",
        "Community Category": "Mature Themes and Adult Content",
        "Member Count": "44211"
    },
    {
        "Subreddit": "r/KazuhaMains",
        "Community Category": "Gaming",
        "Member Count": "44197"
    },
    {
        "Subreddit": "r/UtterlyUniquePhotos",
        "Community Category": "History",
        "Member Count": "44194"
    },
    {
        "Subreddit": "r/foundthehondacivic",
        "Community Category": "Cars and Motor Vehicles",
        "Member Count": "44193"
    },
    {
        "Subreddit": "r/CoolCollections",
        "Community Category": "Hobbies",
        "Member Count": "44187"
    },
    {
        "Subreddit": "r/GayYoungOldDating",
        "Community Category": "Sexual Orientation",
        "Member Count": "44171"
    },
    {
        "Subreddit": "r/ImaginaryArmor",
        "Community Category": "Art",
        "Member Count": "44171"
    },
    {
        "Subreddit": "r/lifeguardkitties",
        "Community Category": "Animals and Pets",
        "Member Count": "44165"
    },
    {
        "Subreddit": "r/HeroForgeMinis",
        "Community Category": "Tabletop Games",
        "Member Count": "44133"
    },
    {
        "Subreddit": "r/AusProperty",
        "Community Category": "Business, Economics, and Finance",
        "Member Count": "44130"
    },
    {
        "Subreddit": "r/VIDEOENGINEERING",
        "Community Category": "Careers",
        "Member Count": "44119"
    },
    {
        "Subreddit": "r/goodrestrictionfood",
        "Community Category": "Food and Drink",
        "Member Count": "44117"
    },
    {
        "Subreddit": "r/LogicPro",
        "Community Category": "Music",
        "Member Count": "44116"
    },
    {
        "Subreddit": "r/FRC",
        "Community Category": "Technology",
        "Member Count": "44091"
    },
    {
        "Subreddit": "r/warcraftrumble",
        "Community Category": "Gaming",
        "Member Count": "44082"
    },
    {
        "Subreddit": "r/SelenaGomezHot",
        "Community Category": "Mature Themes and Adult Content",
        "Member Count": "44065"
    },
    {
        "Subreddit": "r/DoctorMike",
        "Community Category": "Television",
        "Member Count": "44060"
    },
    {
        "Subreddit": "r/wordle",
        "Community Category": "Gaming",
        "Member Count": "44060"
    },
    {
        "Subreddit": "r/LGOLED",
        "Community Category": "Television",
        "Member Count": "44039"
    },
    {
        "Subreddit": "r/Needlefelting",
        "Community Category": "Crafts and DIY",
        "Member Count": "44033"
    },
    {
        "Subreddit": "r/lululemonleggingz",
        "Community Category": "Mature Themes and Adult Content",
        "Member Count": "44029"
    },
    {
        "Subreddit": "r/AMD_Stock",
        "Community Category": "Business, Economics, and Finance",
        "Member Count": "44017"
    },
    {
        "Subreddit": "r/JoshuaWeissman",
        "Community Category": "Food and Drink",
        "Member Count": "44005"
    },
    {
        "Subreddit": "r/DestructiveReaders",
        "Community Category": "Reading, Writing, and Literature",
        "Member Count": "43997"
    },
    {
        "Subreddit": "r/DisneyMirrorverse",
        "Community Category": "Gaming",
        "Member Count": "43985"
    },
    {
        "Subreddit": "r/atoptics",
        "Community Category": "Outdoors and Nature",
        "Member Count": "43970"
    },
    {
        "Subreddit": "r/rainworld",
        "Community Category": "Gaming",
        "Member Count": "43966"
    },
    {
        "Subreddit": "r/twinflames",
        "Community Category": "Family and Relationships",
        "Member Count": "43959"
    },
    {
        "Subreddit": "r/MVIS",
        "Community Category": "Business, Economics, and Finance",
        "Member Count": "43948"
    },
    {
        "Subreddit": "r/CubeWorld",
        "Community Category": "Gaming",
        "Member Count": "43935"
    },
    {
        "Subreddit": "r/8passengersnark",
        "Community Category": "Celebrity",
        "Member Count": "43934"
    },
    {
        "Subreddit": "r/GTA6_NEW",
        "Community Category": "Gaming",
        "Member Count": "43932"
    },
    {
        "Subreddit": "r/Hammers",
        "Community Category": "Sports",
        "Member Count": "43922"
    },
    {
        "Subreddit": "r/forensics",
        "Community Category": "Careers",
        "Member Count": "43920"
    },
    {
        "Subreddit": "r/no",
        "Community Category": "Funny/Humor",
        "Member Count": "43910"
    },
    {
        "Subreddit": "r/FASCAmazon",
        "Community Category": "Careers",
        "Member Count": "43896"
    },
    {
        "Subreddit": "r/thewoodlands",
        "Community Category": "Place",
        "Member Count": "43887"
    },
    {
        "Subreddit": "r/hudsonvalley",
        "Community Category": "Place",
        "Member Count": "43883"
    },
    {
        "Subreddit": "r/WagoonLadies",
        "Community Category": "Fashion",
        "Member Count": "43878"
    },
    {
        "Subreddit": "r/oldmaps",
        "Community Category": "History",
        "Member Count": "43869"
    },
    {
        "Subreddit": "r/AppleArcade",
        "Community Category": "Gaming",
        "Member Count": "43867"
    },
    {
        "Subreddit": "r/SabrinaCarpenter",
        "Community Category": "Celebrity",
        "Member Count": "43842"
    },
    {
        "Subreddit": "r/savannah",
        "Community Category": "Place",
        "Member Count": "43840"
    },
    {
        "Subreddit": "r/iphonehelp",
        "Community Category": "Technology",
        "Member Count": "43838"
    },
    {
        "Subreddit": "r/birdwatching",
        "Community Category": "Hobbies",
        "Member Count": "43828"
    },
    {
        "Subreddit": "r/PatchesEmporium",
        "Community Category": "Gaming",
        "Member Count": "43828"
    },
    {
        "Subreddit": "r/skylanders",
        "Community Category": "Gaming",
        "Member Count": "43828"
    },
    {
        "Subreddit": "r/managers",
        "Community Category": "Careers",
        "Member Count": "43796"
    },
    {
        "Subreddit": "r/ComedyArchaeology",
        "Community Category": "Internet Culture and Memes",
        "Member Count": "43782"
    },
    {
        "Subreddit": "r/Nujabes",
        "Community Category": "Music",
        "Member Count": "43775"
    },
    {
        "Subreddit": "r/creepyvideos",
        "Community Category": "Internet Culture and Memes",
        "Member Count": "43773"
    },
    {
        "Subreddit": "r/redditgetsdrawnbadly",
        "Community Category": "Art",
        "Member Count": "43765"
    },
    {
        "Subreddit": "r/opsec",
        "Community Category": "Technology",
        "Member Count": "43757"
    },
    {
        "Subreddit": "r/fifaclubs",
        "Community Category": "Gaming",
        "Member Count": "43755"
    },
    {
        "Subreddit": "r/KitchenNightmares",
        "Community Category": "Television",
        "Member Count": "43748"
    },
    {
        "Subreddit": "r/monsterhunterclan",
        "Community Category": "Gaming",
        "Member Count": "43747"
    },
    {
        "Subreddit": "r/JohnMulaney",
        "Community Category": "Funny/Humor",
        "Member Count": "43742"
    },
    {
        "Subreddit": "r/CamperVans",
        "Community Category": "Cars and Motor Vehicles",
        "Member Count": "43730"
    },
    {
        "Subreddit": "r/OptionsMillionaire",
        "Community Category": "Business, Economics, and Finance",
        "Member Count": "43697"
    },
    {
        "Subreddit": "r/wine_gaming",
        "Community Category": "Gaming",
        "Member Count": "43692"
    },
    {
        "Subreddit": "r/BananasForScale",
        "Community Category": "Internet Culture and Memes",
        "Member Count": "43690"
    },
    {
        "Subreddit": "r/prochoice",
        "Community Category": "Activism",
        "Member Count": "43681"
    },
    {
        "Subreddit": "r/theketodiet",
        "Community Category": "Food and Drink",
        "Member Count": "43676"
    },
    {
        "Subreddit": "r/DBLegendsReddit",
        "Community Category": "Gaming",
        "Member Count": "43675"
    },
    {
        "Subreddit": "r/dropout",
        "Community Category": "Podcasts and Streamers",
        "Member Count": "43675"
    },
    {
        "Subreddit": "r/WaifuDiffusion",
        "Community Category": "Mature Themes and Adult Content",
        "Member Count": "43675"
    },
    {
        "Subreddit": "r/sillybritishnames",
        "Community Category": "Funny/Humor",
        "Member Count": "43672"
    },
    {
        "Subreddit": "r/arenaofvalor",
        "Community Category": "Gaming",
        "Member Count": "43662"
    },
    {
        "Subreddit": "r/ohnePixel",
        "Community Category": "Podcasts and Streamers",
        "Member Count": "43657"
    },
    {
        "Subreddit": "r/Leadership",
        "Community Category": "Careers",
        "Member Count": "43656"
    },
    {
        "Subreddit": "r/dlsu",
        "Community Category": "Learning and Education",
        "Member Count": "43635"
    },
    {
        "Subreddit": "r/GrowthHacking",
        "Community Category": "Business, Economics, and Finance",
        "Member Count": "43616"
    },
    {
        "Subreddit": "r/texashistory",
        "Community Category": "History",
        "Member Count": "43607"
    },
    {
        "Subreddit": "r/adops",
        "Community Category": "Technology",
        "Member Count": "43596"
    },
    {
        "Subreddit": "r/Boxer",
        "Community Category": "Animals and Pets",
        "Member Count": "43596"
    },
    {
        "Subreddit": "r/decaf",
        "Community Category": "Addiction Support",
        "Member Count": "43596"
    },
    {
        "Subreddit": "r/canceledpod",
        "Community Category": "Podcasts and Streamers",
        "Member Count": "43594"
    },
    {
        "Subreddit": "r/WOSH",
        "Community Category": "Religion and Spirituality",
        "Member Count": "43593"
    },
    {
        "Subreddit": "r/indialesbian",
        "Community Category": "Mature Themes and Adult Content",
        "Member Count": "43587"
    },
    {
        "Subreddit": "r/fican",
        "Community Category": "Business, Economics, and Finance",
        "Member Count": "43561"
    },
    {
        "Subreddit": "r/Dewalt",
        "Community Category": "Crafts and DIY",
        "Member Count": "43547"
    },
    {
        "Subreddit": "r/industrialmusic",
        "Community Category": "Music",
        "Member Count": "43545"
    },
    {
        "Subreddit": "r/britishshorthair",
        "Community Category": "Animals and Pets",
        "Member Count": "43530"
    },
    {
        "Subreddit": "r/soloboardgaming",
        "Community Category": "Tabletop Games",
        "Member Count": "43528"
    },
    {
        "Subreddit": "r/240sx",
        "Community Category": "Cars and Motor Vehicles",
        "Member Count": "43526"
    },
    {
        "Subreddit": "r/WastedGachaTalent",
        "Community Category": "Mature Themes and Adult Content",
        "Member Count": "43519"
    },
    {
        "Subreddit": "r/SeattleKraken",
        "Community Category": "Sports",
        "Member Count": "43505"
    },
    {
        "Subreddit": "r/vertcoin",
        "Community Category": "Crypto",
        "Member Count": "43505"
    },
    {
        "Subreddit": "r/ImaginaryWorlds",
        "Community Category": "Art",
        "Member Count": "43481"
    },
    {
        "Subreddit": "r/bose",
        "Community Category": "Technology",
        "Member Count": "43477"
    },
    {
        "Subreddit": "r/investingforbeginners",
        "Community Category": "Business, Economics, and Finance",
        "Member Count": "43475"
    },
    {
        "Subreddit": "r/FireStickHacks",
        "Community Category": "Technology",
        "Member Count": "43470"
    },
    {
        "Subreddit": "r/BrokeHobbies",
        "Community Category": "Hobbies",
        "Member Count": "43469"
    },
    {
        "Subreddit": "r/starfieldmods",
        "Community Category": "Gaming",
        "Member Count": "43466"
    },
    {
        "Subreddit": "r/GameTrade",
        "Community Category": "Marketplace and Deals",
        "Member Count": "43465"
    },
    {
        "Subreddit": "r/AMABRASIL",
        "Community Category": "Meta/Reddit",
        "Member Count": "43442"
    },
    {
        "Subreddit": "r/OakIsland",
        "Community Category": "Television",
        "Member Count": "43440"
    },
    {
        "Subreddit": "r/DIY_tech",
        "Community Category": "Technology",
        "Member Count": "43427"
    },
    {
        "Subreddit": "r/Clockology",
        "Community Category": "Technology",
        "Member Count": "43418"
    },
    {
        "Subreddit": "r/GranTurismo7",
        "Community Category": "Gaming",
        "Member Count": "43415"
    },
    {
        "Subreddit": "r/footballtactics",
        "Community Category": "Sports",
        "Member Count": "43399"
    },
    {
        "Subreddit": "r/Rockband",
        "Community Category": "Gaming",
        "Member Count": "43396"
    },
    {
        "Subreddit": "r/UnchainedMelancholy",
        "Community Category": "Mature Themes and Adult Content",
        "Member Count": "43370"
    },
    {
        "Subreddit": "r/gametales",
        "Community Category": "Tabletop Games",
        "Member Count": "43366"
    },
    {
        "Subreddit": "r/California_Politics",
        "Community Category": "Politics",
        "Member Count": "43359"
    },
    {
        "Subreddit": "r/MordekaiserMains",
        "Community Category": "Gaming",
        "Member Count": "43357"
    },
    {
        "Subreddit": "r/yorku",
        "Community Category": "Learning and Education",
        "Member Count": "43351"
    },
    {
        "Subreddit": "r/pcmusic",
        "Community Category": "Music",
        "Member Count": "43334"
    },
    {
        "Subreddit": "r/ERAYileBoslugaDogru",
        "Community Category": "Podcasts and Streamers",
        "Member Count": "43331"
    },
    {
        "Subreddit": "r/MandelaCatalogue",
        "Community Category": "Internet Culture and Memes",
        "Member Count": "43329"
    },
    {
        "Subreddit": "r/Eldar",
        "Community Category": "Tabletop Games",
        "Member Count": "43324"
    },
    {
        "Subreddit": "r/parasnailing",
        "Community Category": "Animals and Pets",
        "Member Count": "43324"
    },
    {
        "Subreddit": "r/drivingUK",
        "Community Category": "Cars and Motor Vehicles",
        "Member Count": "43322"
    },
    {
        "Subreddit": "r/fempark",
        "Community Category": "Funny/Humor",
        "Member Count": "43319"
    },
    {
        "Subreddit": "r/denverfood",
        "Community Category": "Food and Drink",
        "Member Count": "43281"
    },
    {
        "Subreddit": "r/CovidVaccinated",
        "Community Category": "Medical and Mental Health",
        "Member Count": "43264"
    },
    {
        "Subreddit": "r/Eddsworld",
        "Community Category": "Podcasts and Streamers",
        "Member Count": "43251"
    },
    {
        "Subreddit": "r/EliteMiners",
        "Community Category": "Gaming",
        "Member Count": "43250"
    },
    {
        "Subreddit": "r/Steelbooks",
        "Community Category": "Movies",
        "Member Count": "43244"
    },
    {
        "Subreddit": "r/applewatchfaces",
        "Community Category": "Technology",
        "Member Count": "43241"
    },
    {
        "Subreddit": "r/VintageTees",
        "Community Category": "Fashion",
        "Member Count": "43234"
    },
    {
        "Subreddit": "r/Pacybits",
        "Community Category": "Technology",
        "Member Count": "43218"
    },
    {
        "Subreddit": "r/Bluray",
        "Community Category": "Movies",
        "Member Count": "43217"
    },
    {
        "Subreddit": "r/kingcobrajfs",
        "Community Category": "Internet Culture and Memes",
        "Member Count": "43193"
    },
    {
        "Subreddit": "r/GoodValue",
        "Community Category": "Marketplace and Deals",
        "Member Count": "43189"
    },
    {
        "Subreddit": "r/warcraft3",
        "Community Category": "Gaming",
        "Member Count": "43172"
    },
    {
        "Subreddit": "r/AlfaRomeo",
        "Community Category": "Cars and Motor Vehicles",
        "Member Count": "43168"
    },
    {
        "Subreddit": "r/EKGs",
        "Community Category": "Medical and Mental Health",
        "Member Count": "43159"
    },
    {
        "Subreddit": "r/NorthKoreaPics",
        "Community Category": "Place",
        "Member Count": "43137"
    },
    {
        "Subreddit": "r/CK2GameOfthrones",
        "Community Category": "Gaming",
        "Member Count": "43126"
    },
    {
        "Subreddit": "r/Sauna",
        "Community Category": "Hobbies",
        "Member Count": "43117"
    },
    {
        "Subreddit": "r/Appliances",
        "Community Category": "Home and Garden",
        "Member Count": "43113"
    },
    {
        "Subreddit": "r/f45",
        "Community Category": "Fitness and Nutrition",
        "Member Count": "43108"
    },
    {
        "Subreddit": "r/DrewGooden",
        "Community Category": "Podcasts and Streamers",
        "Member Count": "43088"
    },
    {
        "Subreddit": "r/NBATalk",
        "Community Category": "Sports",
        "Member Count": "43077"
    },
    {
        "Subreddit": "r/ScaramoucheMains",
        "Community Category": "Gaming",
        "Member Count": "43066"
    },
    {
        "Subreddit": "r/Cursedgunimages",
        "Community Category": "Internet Culture and Memes",
        "Member Count": "43055"
    },
    {
        "Subreddit": "r/OldSkaters",
        "Community Category": "Hobbies",
        "Member Count": "43029"
    },
    {
        "Subreddit": "r/legogaming",
        "Community Category": "Gaming",
        "Member Count": "43017"
    },
    {
        "Subreddit": "r/collegeresults",
        "Community Category": "Learning and Education",
        "Member Count": "43013"
    },
    {
        "Subreddit": "r/maui",
        "Community Category": "Place",
        "Member Count": "42996"
    },
    {
        "Subreddit": "r/Celebrity_Cleavage",
        "Community Category": "Mature Themes and Adult Content",
        "Member Count": "42994"
    },
    {
        "Subreddit": "r/aircrashinvestigation",
        "Community Category": "Learning and Education",
        "Member Count": "42981"
    },
    {
        "Subreddit": "r/TomorrowByTogether",
        "Community Category": "Celebrity",
        "Member Count": "42980"
    },
    {
        "Subreddit": "r/askaustin",
        "Community Category": "Place",
        "Member Count": "42962"
    },
    {
        "Subreddit": "r/quiteinteresting",
        "Community Category": "Television",
        "Member Count": "42944"
    },
    {
        "Subreddit": "r/starfinder_rpg",
        "Community Category": "Tabletop Games",
        "Member Count": "42921"
    },
    {
        "Subreddit": "r/OurFlagMeansDeath",
        "Community Category": "Television",
        "Member Count": "42907"
    },
    {
        "Subreddit": "r/psychologyofsex",
        "Community Category": "Science",
        "Member Count": "42906"
    },
    {
        "Subreddit": "r/bigfloppa",
        "Community Category": "Internet Culture and Memes",
        "Member Count": "42904"
    },
    {
        "Subreddit": "r/fatcats",
        "Community Category": "Animals and Pets",
        "Member Count": "42895"
    },
    {
        "Subreddit": "r/KpopHotties",
        "Community Category": "Celebrity",
        "Member Count": "42894"
    },
    {
        "Subreddit": "r/chronotrigger",
        "Community Category": "Gaming",
        "Member Count": "42890"
    }
]