[
    {
        "Subreddit": "r/Scrolls",
        "Community Category": "Gaming",
        "Member Count": "3281"
    },
    {
        "Subreddit": "r/The_Frank",
        "Community Category": "The_Frank, where you will see the TRUE GOD.",
        "Member Count": "3281"
    },
    {
        "Subreddit": "r/Carnatic",
        "Community Category": "Music",
        "Member Count": "3280"
    },
    {
        "Subreddit": "r/EudoxiaMysteries",
        "Community Category": "Internet Culture and Memes",
        "Member Count": "3280"
    },
    {
        "Subreddit": "r/NorseMemes",
        "Community Category": "Funny/Humor",
        "Member Count": "3280"
    },
    {
        "Subreddit": "r/OlympiakosFC",
        "Community Category": "Sports",
        "Member Count": "3280"
    },
    {
        "Subreddit": "r/resolume",
        "Community Category": "Programming",
        "Member Count": "3280"
    },
    {
        "Subreddit": "r/spaceandtimeDB",
        "Community Category": "Space and Time is the Verifiable Compute Layer for AI x Blockchain.\n\nhttps://spaceandtime.io",
        "Member Count": "3280"
    },
    {
        "Subreddit": "r/AriaKarizma",
        "Community Category": "Podcasts and Streamers",
        "Member Count": "3279"
    },
    {
        "Subreddit": "r/Breadbug",
        "Community Category": "Internet Culture and Memes",
        "Member Count": "3279"
    },
    {
        "Subreddit": "r/lookwhoimet",
        "Community Category": "A place to show where you, who you, and when you saw a celebrity or important figure.",
        "Member Count": "3279"
    },
    {
        "Subreddit": "r/MildlyUncomfortable",
        "Community Category": "This is a place to post pictures that are uncomfortable, but not in a way that can make you cringe.",
        "Member Count": "3279"
    },
    {
        "Subreddit": "r/soundslikeacultpod",
        "Community Category": "Podcasts and Streamers",
        "Member Count": "3279"
    },
    {
        "Subreddit": "r/GMOMyths",
        "Community Category": "Science",
        "Member Count": "3278"
    },
    {
        "Subreddit": "r/ShulisAnonymous",
        "Community Category": "Podcasts and Streamers",
        "Member Count": "3278"
    },
    {
        "Subreddit": "r/AngelInvesting",
        "Community Category": "Business, Economics, and Finance",
        "Member Count": "3277"
    },
    {
        "Subreddit": "r/Atomicrops",
        "Community Category": "Gaming",
        "Member Count": "3277"
    },
    {
        "Subreddit": "r/badrealtexts",
        "Community Category": "Funny/Humor",
        "Member Count": "3277"
    },
    {
        "Subreddit": "r/BeyondTheBumpUK",
        "Community Category": "Family and Relationships",
        "Member Count": "3277"
    },
    {
        "Subreddit": "r/digitalanthro",
        "Community Category": "Learning and Education",
        "Member Count": "3277"
    },
    {
        "Subreddit": "r/nano",
        "Community Category": "Science",
        "Member Count": "3277"
    },
    {
        "Subreddit": "r/ymgroup",
        "Community Category": "\u6b22\u8fce\u6765\u5230\u6da6\u7ec4\uff08\u53c8\u79f0ym\u6216\u6768\u5e42\u7ec4\uff09\uff0c\u5982\u679c\u4f60\u4e5f\u662f\u6253\u7b97\u6da6\u7684\u5c0f\u4f19\u4f34\uff0c\u53ef\u4ee5\u79c1\u4fe1\u7ec4\u957f\u8fdb\u79fb\u6c11\u5fae\u4fe1\u7fa4\uff0c\u7ec4\u961f\u6da6\u4e4b\u3002\ntg\u7fa4\uff1ahttps://t.me/+nqULJIb-Zj82YTQx\n\u8096\u7533\u514b\u8fd9\u4e2a\u5730\u65b9\uff0c\u4e5f\u5e76\u4e0d\u90fd\u90a3\u4e48\u7cdf\u7cd5\uff0c\u5076\u5c14\uff0c\u4f60\u80fd\u542c\u5230\u6b4c\u5267\u5531\u7247\u91cc\u7684\u610f\u5927\u5229\u5973\u4eba\u5f15\u542d\u9ad8\u6b4c\uff0c\u751a\u81f3\uff0c\u6709\u65f6\u8fd8\u80fd\u5728\u52b3\u788c\u4e00\u5929\u540e\uff0c\u5728\u5929\u53f0\u4e0a\u4eab\u53d7\u4e00\u4e0b\u6e05\u51c9\u7684\u5564\u9152\u548c\u7247\u523b\u5b89\u9038\uff0c\u8fd9\u6211\u90fd\u660e\u767d\u3002\u4f46\uff0c\u4f60\u5f97\u77e5\u9053\uff0c\u65e0\u8bba\u5564\u9152\u591a\u597d\u559d\uff0c\u610f\u5927\u5229\u5973\u4eba\u7684\u58f0\u97f3\u591a\u4e48\u52a8\u4eba\uff0c\u8fd9\u91cc\u59cb\u7ec8\u662f\u8096\u7533\u514b\u3002\u800c\u4f60\u66f4\u5e94\u8be5\u8bb0\u4f4f\uff0c\u8fd9\u4e2a\u4e16\u754c\u4e0a\uff0c\u4f9d\u7136\u5b58\u5728\u4e0d\u662f\u7528\u77f3\u5934\u56f4\u8d77\u6765\u7684\u5730\u65b9\u2014\u2014\u5373\u4fbf\u50cf\u5b89\u8fea\u90a3\u6837\u82b1\u53bb\u5341\u4e5d\u5e74\uff0c\u5b83\u4eec\u4f9d\u7136\u662f\u503c\u5f97\u7684\uff01\n\n\u5e0c\u671b\uff0c\u6709\u5929\u80fd\u5728\u6d77\u8fb9\u90a3\u8258\u7834\u8239\u8fb9\u4e0a\u548c\u4f60\u4eec\u4e00\u8d77\u559d\u5564\u9152\u3002 \n\n\u6da6\uff0c\u6216\u8005\u7559\u4e0b\u4e86\u5750\u7262\uff0c\u662f\u5f53\u4ee3\u4e2d\u56fd\u5e74\u8f7b\u4eba\u552f\u4e8c\u7684\u51fa\u8def\u3002",
        "Member Count": "3277"
    },
    {
        "Subreddit": "r/Deaths_Gambit",
        "Community Category": "Gaming",
        "Member Count": "3276"
    },
    {
        "Subreddit": "r/hvdsqcmve",
        "Community Category": "your chance to \"blow\"\nhttps://t.me/+vz05LgwYp5JmNjg0",
        "Member Count": "3276"
    },
    {
        "Subreddit": "r/Yojamba",
        "Community Category": "Gaming",
        "Member Count": "3276"
    },
    {
        "Subreddit": "r/AgameofthronesLCG",
        "Community Category": "Gaming",
        "Member Count": "3275"
    },
    {
        "Subreddit": "r/astonvilla",
        "Community Category": "Sports",
        "Member Count": "3275"
    },
    {
        "Subreddit": "r/Canonn",
        "Community Category": "Originally drawn together from the four corners of inhabited space to investigate the Unknown Artefacts, the Canonn consists of commanders from all professions, all allegiances, and all walks of life. One common goal unites them: to seek the truth behind the galaxy's mysteries at any cost.",
        "Member Count": "3275"
    },
    {
        "Subreddit": "r/GrumpyCat",
        "Community Category": "Internet Culture and Memes",
        "Member Count": "3275"
    },
    {
        "Subreddit": "r/stuffgettingyeeted",
        "Community Category": "Funny/Humor",
        "Member Count": "3275"
    },
    {
        "Subreddit": "r/WarDragons",
        "Community Category": "Gaming",
        "Member Count": "3275"
    },
    {
        "Subreddit": "r/AnimesYoutube",
        "Community Category": "Mature Themes and Adult Content",
        "Member Count": "3274"
    },
    {
        "Subreddit": "r/bbby_remastered",
        "Community Category": "Business, Economics, and Finance",
        "Member Count": "3274"
    },
    {
        "Subreddit": "r/BPDFamily",
        "Community Category": "Family and Relationships",
        "Member Count": "3274"
    },
    {
        "Subreddit": "r/fortSALTA",
        "Community Category": "Anime",
        "Member Count": "3274"
    },
    {
        "Subreddit": "r/Futurelings",
        "Community Category": "Podcasts and Streamers",
        "Member Count": "3274"
    },
    {
        "Subreddit": "r/haikuOS",
        "Community Category": "Technology",
        "Member Count": "3274"
    },
    {
        "Subreddit": "r/melatonin",
        "Community Category": "Medical and Mental Health",
        "Member Count": "3274"
    },
    {
        "Subreddit": "r/PaigePorcelain_05",
        "Community Category": "Mature Themes and Adult Content",
        "Member Count": "3274"
    },
    {
        "Subreddit": "r/PedalDemos",
        "Community Category": "Music",
        "Member Count": "3274"
    },
    {
        "Subreddit": "r/SEARS",
        "Community Category": "Marketplace and Deals",
        "Member Count": "3274"
    },
    {
        "Subreddit": "r/unm",
        "Community Category": "Learning and Education",
        "Member Count": "3274"
    },
    {
        "Subreddit": "r/voidtrain",
        "Community Category": "Gaming",
        "Member Count": "3274"
    },
    {
        "Subreddit": "r/Arnhem",
        "Community Category": "Place",
        "Member Count": "3273"
    },
    {
        "Subreddit": "r/Geneology",
        "Community Category": "Family and Relationships",
        "Member Count": "3273"
    },
    {
        "Subreddit": "r/Kourtney_Kellar",
        "Community Category": "Mature Themes and Adult Content",
        "Member Count": "3273"
    },
    {
        "Subreddit": "r/ROSHTEIN",
        "Community Category": "Mature Themes and Adult Content",
        "Member Count": "3273"
    },
    {
        "Subreddit": "r/seconddinner",
        "Community Category": "Discussion and News about Second Dinner - a new game studio!",
        "Member Count": "3273"
    },
    {
        "Subreddit": "r/TZM",
        "Community Category": "Activism",
        "Member Count": "3273"
    },
    {
        "Subreddit": "r/AppreciateGreatness",
        "Community Category": "Mature Themes and Adult Content",
        "Member Count": "3272"
    },
    {
        "Subreddit": "r/fullconcertonyoutube",
        "Community Category": "Post youtube links to full length shows",
        "Member Count": "3272"
    },
    {
        "Subreddit": "r/redheeler",
        "Community Category": "Animals and Pets",
        "Member Count": "3272"
    },
    {
        "Subreddit": "r/thqtty",
        "Community Category": "Celebrity",
        "Member Count": "3272"
    },
    {
        "Subreddit": "r/Anatomy4Sculptors",
        "Community Category": "Welcome to Anatomy4Sculptors",
        "Member Count": "3271"
    },
    {
        "Subreddit": "r/andreadalmau",
        "Community Category": "Mature Themes and Adult Content",
        "Member Count": "3271"
    },
    {
        "Subreddit": "r/DaltonGA",
        "Community Category": "Carpet Capital of the World, 32nd largest city in GA, and THREE WALMARTS!",
        "Member Count": "3271"
    },
    {
        "Subreddit": "r/Medical_Students",
        "Community Category": "Learning and Education",
        "Member Count": "3271"
    },
    {
        "Subreddit": "r/passau",
        "Community Category": "Place",
        "Member Count": "3271"
    },
    {
        "Subreddit": "r/skinks",
        "Community Category": "Animals and Pets",
        "Member Count": "3271"
    },
    {
        "Subreddit": "r/AthleticClub",
        "Community Category": "Sports",
        "Member Count": "3270"
    },
    {
        "Subreddit": "r/BonJovi",
        "Community Category": "Music",
        "Member Count": "3270"
    },
    {
        "Subreddit": "r/GolfStory",
        "Community Category": "Gaming",
        "Member Count": "3270"
    },
    {
        "Subreddit": "r/LLVM",
        "Community Category": "Programming",
        "Member Count": "3270"
    },
    {
        "Subreddit": "r/Poconos",
        "Community Category": "Place",
        "Member Count": "3270"
    },
    {
        "Subreddit": "r/allowedsnacks",
        "Community Category": "A subreddit for food that looks like inedible objects.\n\nBasically, it's the opposite of /r/forbiddensnacks.",
        "Member Count": "3269"
    },
    {
        "Subreddit": "r/AnimalCrossingAmiibos",
        "Community Category": "Gaming",
        "Member Count": "3269"
    },
    {
        "Subreddit": "r/ashleycarnduff",
        "Community Category": "Podcasts and Streamers",
        "Member Count": "3269"
    },
    {
        "Subreddit": "r/Fightsgonewildarchive",
        "Community Category": "Internet Culture and Memes",
        "Member Count": "3269"
    },
    {
        "Subreddit": "r/pcabominations",
        "Community Category": "Technology",
        "Member Count": "3269"
    },
    {
        "Subreddit": "r/STGFamily",
        "Community Category": "Welcome to SimbaThaGod's official reddit server. Every Friday,  Simba will react to the memes, artwork, and other stuff created and posted in the reddit.",
        "Member Count": "3269"
    },
    {
        "Subreddit": "r/Forth",
        "Community Category": "Programming",
        "Member Count": "3268"
    },
    {
        "Subreddit": "r/nujijinactie",
        "Community Category": "Welcome to nujijinactie",
        "Member Count": "3268"
    },
    {
        "Subreddit": "r/Trick2g",
        "Community Category": "Podcasts and Streamers",
        "Member Count": "3268"
    },
    {
        "Subreddit": "r/unicorn",
        "Community Category": "Internet Culture and Memes",
        "Member Count": "3268"
    },
    {
        "Subreddit": "r/blightsurvival",
        "Community Category": "Gaming",
        "Member Count": "3267"
    },
    {
        "Subreddit": "r/BoneHurtJuice",
        "Community Category": "Funny/Humor",
        "Member Count": "3267"
    },
    {
        "Subreddit": "r/IASIPrequelMemes",
        "Community Category": "It's Always Sunny in Philadelphia based Prequel Memes, Prequel based It's Always Sunny in Philadelphia Memes",
        "Member Count": "3267"
    },
    {
        "Subreddit": "r/kava_platform",
        "Community Category": "Crypto",
        "Member Count": "3267"
    },
    {
        "Subreddit": "r/kristinaewing",
        "Community Category": "linktr.ee/kristina_ewing",
        "Member Count": "3267"
    },
    {
        "Subreddit": "r/LAfoodies",
        "Community Category": "Foodies in Los Angeles.",
        "Member Count": "3267"
    },
    {
        "Subreddit": "r/BitcoinDeFi",
        "Community Category": "Crypto",
        "Member Count": "3266"
    },
    {
        "Subreddit": "r/HKUniversity",
        "Community Category": "Learning and Education",
        "Member Count": "3266"
    },
    {
        "Subreddit": "r/iMovie",
        "Community Category": "Technology",
        "Member Count": "3266"
    },
    {
        "Subreddit": "r/LowSelfEsteem",
        "Community Category": "Medical and Mental Health",
        "Member Count": "3266"
    },
    {
        "Subreddit": "r/next_time_eat_a_salad",
        "Community Category": "Funny/Humor",
        "Member Count": "3266"
    },
    {
        "Subreddit": "r/PhoenixTheBand",
        "Community Category": "Music",
        "Member Count": "3266"
    },
    {
        "Subreddit": "r/PinoyDramarama",
        "Community Category": "Because teleseryes nowadays don't only exist on TV.",
        "Member Count": "3266"
    },
    {
        "Subreddit": "r/BoulderingVideos",
        "Community Category": "Sports",
        "Member Count": "3265"
    },
    {
        "Subreddit": "r/CloneDrone",
        "Community Category": "Gaming",
        "Member Count": "3265"
    },
    {
        "Subreddit": "r/extrasbeingextra",
        "Community Category": "Film and television extras going the extra mile",
        "Member Count": "3265"
    },
    {
        "Subreddit": "r/FlorenceAl",
        "Community Category": "Place",
        "Member Count": "3265"
    },
    {
        "Subreddit": "r/FloridaBarExam",
        "Community Category": "Learning and Education",
        "Member Count": "3265"
    },
    {
        "Subreddit": "r/conorleslie",
        "Community Category": "Celebrity",
        "Member Count": "3264"
    },
    {
        "Subreddit": "r/peachytoes",
        "Community Category": "Animals and Pets",
        "Member Count": "3264"
    },
    {
        "Subreddit": "r/ps1",
        "Community Category": "Gaming",
        "Member Count": "3264"
    },
    {
        "Subreddit": "r/trustedhousesitters",
        "Community Category": "Business, Economics, and Finance",
        "Member Count": "3264"
    },
    {
        "Subreddit": "r/ai_trading",
        "Community Category": "Business, Economics, and Finance",
        "Member Count": "3263"
    },
    {
        "Subreddit": "r/ChrisHemsworth",
        "Community Category": "Celebrity",
        "Member Count": "3263"
    },
    {
        "Subreddit": "r/GarageDoorService",
        "Community Category": "Home and Garden",
        "Member Count": "3263"
    },
    {
        "Subreddit": "r/indepthaskreddit",
        "Community Category": "Meta/Reddit",
        "Member Count": "3263"
    },
    {
        "Subreddit": "r/pen",
        "Community Category": "Hobbies",
        "Member Count": "3263"
    },
    {
        "Subreddit": "r/TheGatewayTapes",
        "Community Category": "Dive into consciousness exploration in a laid-back, open-minded, and supportive community.",
        "Member Count": "3263"
    },
    {
        "Subreddit": "r/YouHaveBeenBamboozled",
        "Community Category": "Meta/Reddit",
        "Member Count": "3263"
    },
    {
        "Subreddit": "r/amsterdamsgarden",
        "Community Category": "Amsterdam's Garden is a top ranked medical marijuana dispensary in San Jose, California. There are numerous strains, waxes and edibles.",
        "Member Count": "3262"
    },
    {
        "Subreddit": "r/ayyrosaline",
        "Community Category": "Welcome to ayyrosaline",
        "Member Count": "3262"
    },
    {
        "Subreddit": "r/BitcoinUSA",
        "Community Category": "The official reddit Bitcoin Community for these United States of America!",
        "Member Count": "3262"
    },
    {
        "Subreddit": "r/MNMD",
        "Community Category": "Post anything. Enjoy true free discussion.",
        "Member Count": "3262"
    },
    {
        "Subreddit": "r/PythonHelpForCash",
        "Community Category": "Welcome to PythonHelpForCash",
        "Member Count": "3262"
    },
    {
        "Subreddit": "r/sciencebasedparentALL",
        "Community Category": "Family and Relationships",
        "Member Count": "3262"
    },
    {
        "Subreddit": "r/TheLongestGameEver2",
        "Community Category": "Gaming",
        "Member Count": "3262"
    },
    {
        "Subreddit": "r/Wardruna",
        "Community Category": "Music",
        "Member Count": "3262"
    },
    {
        "Subreddit": "r/circular_economy",
        "Community Category": "Business, Economics, and Finance",
        "Member Count": "3261"
    },
    {
        "Subreddit": "r/GlassNegativeEra",
        "Community Category": "History",
        "Member Count": "3261"
    },
    {
        "Subreddit": "r/grpc",
        "Community Category": "Programming",
        "Member Count": "3261"
    },
    {
        "Subreddit": "r/pixel_dailies",
        "Community Category": "Art",
        "Member Count": "3261"
    },
    {
        "Subreddit": "r/tampajobs",
        "Community Category": "Careers",
        "Member Count": "3261"
    },
    {
        "Subreddit": "r/ToppsMarvelCollect",
        "Community Category": "Hobbies",
        "Member Count": "3261"
    },
    {
        "Subreddit": "r/GabrielaHella",
        "Community Category": "Mature Themes and Adult Content",
        "Member Count": "3260"
    },
    {
        "Subreddit": "r/pathfinder_lfg",
        "Community Category": "Gaming",
        "Member Count": "3260"
    },
    {
        "Subreddit": "r/Somerset",
        "Community Category": "Place",
        "Member Count": "3260"
    },
    {
        "Subreddit": "r/ThailandPics",
        "Community Category": "A subreddit dedicated to photographs of The Kingdom of Thailand! \n\nMember of the /r/NationalPhotoSubs network.",
        "Member Count": "3260"
    },
    {
        "Subreddit": "r/cewpins",
        "Community Category": "Podcasts and Streamers",
        "Member Count": "3259"
    },
    {
        "Subreddit": "r/ChryslerPacifica",
        "Community Category": "Cars and Motor Vehicles",
        "Member Count": "3259"
    },
    {
        "Subreddit": "r/codmobilememes",
        "Community Category": "Your hub for fresh COD Mobile memes everyday",
        "Member Count": "3259"
    },
    {
        "Subreddit": "r/dudeperfect",
        "Community Category": "Sports",
        "Member Count": "3259"
    },
    {
        "Subreddit": "r/GameMods",
        "Community Category": "Gaming",
        "Member Count": "3259"
    },
    {
        "Subreddit": "r/gamesworkshop",
        "Community Category": "Tabletop Games",
        "Member Count": "3259"
    },
    {
        "Subreddit": "r/HorizonZeroDawn_PC",
        "Community Category": "Gaming",
        "Member Count": "3259"
    },
    {
        "Subreddit": "r/ChaosConquest",
        "Community Category": "Gaming",
        "Member Count": "3258"
    },
    {
        "Subreddit": "r/DadsGaming",
        "Community Category": "Gaming",
        "Member Count": "3258"
    },
    {
        "Subreddit": "r/Entrapta",
        "Community Category": "Television",
        "Member Count": "3258"
    },
    {
        "Subreddit": "r/FranchiseHockey",
        "Community Category": "Gaming",
        "Member Count": "3258"
    },
    {
        "Subreddit": "r/LangfordBC",
        "Community Category": "Place",
        "Member Count": "3258"
    },
    {
        "Subreddit": "r/ModafinilOPENTALK",
        "Community Category": "Learning and Education",
        "Member Count": "3258"
    },
    {
        "Subreddit": "r/Playmobil",
        "Community Category": "Hobbies",
        "Member Count": "3258"
    },
    {
        "Subreddit": "r/AndroidVR",
        "Community Category": "Technology",
        "Member Count": "3257"
    },
    {
        "Subreddit": "r/Voat",
        "Community Category": "Welcome to Voat",
        "Member Count": "3257"
    },
    {
        "Subreddit": "r/YourBudTevin",
        "Community Category": "Podcasts and Streamers",
        "Member Count": "3257"
    },
    {
        "Subreddit": "r/altoona",
        "Community Category": "Place",
        "Member Count": "3256"
    },
    {
        "Subreddit": "r/CobraKai_Memes",
        "Community Category": "Internet Culture and Memes",
        "Member Count": "3256"
    },
    {
        "Subreddit": "r/FlipaClip",
        "Community Category": "Technology",
        "Member Count": "3256"
    },
    {
        "Subreddit": "r/jisamsssss",
        "Community Category": "Welcome to jisamsssss",
        "Member Count": "3256"
    },
    {
        "Subreddit": "r/mixedmedia",
        "Community Category": "Art",
        "Member Count": "3256"
    },
    {
        "Subreddit": "r/popmusic",
        "Community Category": "Welcome to popmusic",
        "Member Count": "3256"
    },
    {
        "Subreddit": "r/89SQUAD89",
        "Community Category": "Celebrity",
        "Member Count": "3255"
    },
    {
        "Subreddit": "r/animewomeninsuits",
        "Community Category": "Anime",
        "Member Count": "3255"
    },
    {
        "Subreddit": "r/Forsvaret",
        "Community Category": "Military",
        "Member Count": "3255"
    },
    {
        "Subreddit": "r/GibiASMR_",
        "Community Category": "Mature Themes and Adult Content",
        "Member Count": "3255"
    },
    {
        "Subreddit": "r/lancashire",
        "Community Category": "Place",
        "Member Count": "3255"
    },
    {
        "Subreddit": "r/Memesana",
        "Community Category": "Internet Culture and Memes",
        "Member Count": "3255"
    },
    {
        "Subreddit": "r/stillwoozy",
        "Community Category": "Music",
        "Member Count": "3255"
    },
    {
        "Subreddit": "r/TaylorSwiftDrop",
        "Community Category": "Celebrity",
        "Member Count": "3255"
    },
    {
        "Subreddit": "r/TUYU_official",
        "Community Category": "Music",
        "Member Count": "3255"
    },
    {
        "Subreddit": "r/AllPainNoGain",
        "Community Category": "Funny/Humor",
        "Member Count": "3254"
    },
    {
        "Subreddit": "r/chiselsandbits",
        "Community Category": "Gaming",
        "Member Count": "3254"
    },
    {
        "Subreddit": "r/Discgolfauctions",
        "Community Category": "Sports",
        "Member Count": "3254"
    },
    {
        "Subreddit": "r/EU4Multi",
        "Community Category": "Gaming",
        "Member Count": "3254"
    },
    {
        "Subreddit": "r/PrettySissyAcademy",
        "Community Category": "Welcome to the online home of Selene\u2019s Sissy Academy. A school for men and boys who are fed up with their masculinity and want to delve deep into their femininity.\n\nEnthusiasm and a desire to learn are qualities we look for in students. In a positive setting, we\u2019ll provide the direction, teach you about the wigs, and clothing. We\u2019ll prepare you for your first day out as a tempting Woman.",
        "Member Count": "3254"
    },
    {
        "Subreddit": "r/KeyShot",
        "Community Category": "Technology",
        "Member Count": "3253"
    },
    {
        "Subreddit": "r/nijahownsaglock2",
        "Community Category": "Welcome to nijahownsaglock2",
        "Member Count": "3253"
    },
    {
        "Subreddit": "r/RomanceMangaAnime",
        "Community Category": "Anime",
        "Member Count": "3253"
    },
    {
        "Subreddit": "r/YahLahBut",
        "Community Category": "Podcasts and Streamers",
        "Member Count": "3253"
    },
    {
        "Subreddit": "r/DistroTube",
        "Community Category": "Podcasts and Streamers",
        "Member Count": "3252"
    },
    {
        "Subreddit": "r/HOSPITAL",
        "Community Category": "Medical and Mental Health",
        "Member Count": "3252"
    },
    {
        "Subreddit": "r/OtterlyHuman",
        "Community Category": "Funny/Humor",
        "Member Count": "3252"
    },
    {
        "Subreddit": "r/UltimateNurse",
        "Community Category": "Gaming",
        "Member Count": "3252"
    },
    {
        "Subreddit": "r/AccidentalGhibli",
        "Community Category": "Photos & videos that look like they came straight out of a Studio Ghibli film.",
        "Member Count": "3251"
    },
    {
        "Subreddit": "r/asustor",
        "Community Category": "Technology",
        "Member Count": "3251"
    },
    {
        "Subreddit": "r/BeatTheMonkeysPaw",
        "Community Category": "Meta/Reddit",
        "Member Count": "3251"
    },
    {
        "Subreddit": "r/Pixio_Gaming",
        "Community Category": "Gaming",
        "Member Count": "3251"
    },
    {
        "Subreddit": "r/Virathindumemes",
        "Community Category": "Internet Culture and Memes",
        "Member Count": "3251"
    },
    {
        "Subreddit": "r/bsv",
        "Community Category": "Crypto",
        "Member Count": "3250"
    },
    {
        "Subreddit": "r/Clubhouseguide",
        "Community Category": "Social Audio subreddit. Tips, Tricks & everything social audio related to Reddit Talks, Clubhouse, Twitter Spaces, Spotify Live, Amazon Amp, and more.",
        "Member Count": "3250"
    },
    {
        "Subreddit": "r/heartstoppersyndrome",
        "Community Category": "Television",
        "Member Count": "3250"
    },
    {
        "Subreddit": "r/infinitypool",
        "Community Category": "Business, Economics, and Finance",
        "Member Count": "3250"
    },
    {
        "Subreddit": "r/TorbjornMains",
        "Community Category": "Gaming",
        "Member Count": "3250"
    },
    {
        "Subreddit": "r/InfinitePainter",
        "Community Category": "Art",
        "Member Count": "3249"
    },
    {
        "Subreddit": "r/ReaperMiniatures",
        "Community Category": "Tabletop Games",
        "Member Count": "3249"
    },
    {
        "Subreddit": "r/GenesisGV70",
        "Community Category": "Cars and Motor Vehicles",
        "Member Count": "3248"
    },
    {
        "Subreddit": "r/80sHipHop",
        "Community Category": "Music",
        "Member Count": "3247"
    },
    {
        "Subreddit": "r/analogphotography",
        "Community Category": "A subreddit for Analog Photography. Shooting on film, developing and printing. Feel free to share your photographs, ask questions, and discuss.",
        "Member Count": "3247"
    },
    {
        "Subreddit": "r/BallState",
        "Community Category": "Learning and Education",
        "Member Count": "3247"
    },
    {
        "Subreddit": "r/caloriedeficit",
        "Community Category": "Fitness and Nutrition",
        "Member Count": "3247"
    },
    {
        "Subreddit": "r/DeathAndTaxesMTG",
        "Community Category": "Gaming",
        "Member Count": "3247"
    },
    {
        "Subreddit": "r/FemalePhysicians",
        "Community Category": "Careers",
        "Member Count": "3247"
    },
    {
        "Subreddit": "r/GirlsLikeGirls",
        "Community Category": "A safe space for sapphic women and non-binary people to come together and celebrate our love and relationships.",
        "Member Count": "3247"
    },
    {
        "Subreddit": "r/tickettoride",
        "Community Category": "Tabletop Games",
        "Member Count": "3247"
    },
    {
        "Subreddit": "r/confessions__za",
        "Community Category": "South Africa\u2019s official confessions.za page",
        "Member Count": "3246"
    },
    {
        "Subreddit": "r/KOSSstock",
        "Community Category": "Business, Economics, and Finance",
        "Member Count": "3246"
    },
    {
        "Subreddit": "r/watertownny",
        "Community Category": "Place",
        "Member Count": "3246"
    },
    {
        "Subreddit": "r/PixelPeople",
        "Community Category": "Gaming",
        "Member Count": "3245"
    },
    {
        "Subreddit": "r/PokeCodes",
        "Community Category": "A place to promote socials, grow a following, or just make someone's day by sharing Pokemon TCG codes.",
        "Member Count": "3245"
    },
    {
        "Subreddit": "r/ProphetsForProfit",
        "Community Category": "Funny/Humor",
        "Member Count": "3245"
    },
    {
        "Subreddit": "r/rollsomememes",
        "Community Category": "Internet Culture and Memes",
        "Member Count": "3245"
    },
    {
        "Subreddit": "r/TLOPO",
        "Community Category": "Gaming",
        "Member Count": "3245"
    },
    {
        "Subreddit": "r/chilly",
        "Community Category": "The sub to praise everyone's favorite snowman, Chilly from the Kirby series.",
        "Member Count": "3244"
    },
    {
        "Subreddit": "r/ChurchOfTooru",
        "Community Category": "Anime",
        "Member Count": "3244"
    },
    {
        "Subreddit": "r/FortCollinsClassified",
        "Community Category": "Marketplace and Deals",
        "Member Count": "3244"
    },
    {
        "Subreddit": "r/lasskicker",
        "Community Category": "Sports",
        "Member Count": "3244"
    },
    {
        "Subreddit": "r/LeftyEcon",
        "Community Category": "Business, Economics, and Finance",
        "Member Count": "3244"
    },
    {
        "Subreddit": "r/RelientK",
        "Community Category": "Music",
        "Member Count": "3244"
    },
    {
        "Subreddit": "r/90sNostalgia",
        "Community Category": "Welcome to 90sNostalgia",
        "Member Count": "3243"
    },
    {
        "Subreddit": "r/Anatolianarchaeology",
        "Community Category": "Science",
        "Member Count": "3243"
    },
    {
        "Subreddit": "r/disneyfood",
        "Community Category": "Your source for some of the best meals, restaurants, or snacks that the most magical places on earth have to offer.",
        "Member Count": "3243"
    },
    {
        "Subreddit": "r/JustNoHOA",
        "Community Category": "Home and Garden",
        "Member Count": "3243"
    },
    {
        "Subreddit": "r/neology",
        "Community Category": "Welcome to neology",
        "Member Count": "3243"
    },
    {
        "Subreddit": "r/scandinavianbeauties",
        "Community Category": "Mature Themes and Adult Content",
        "Member Count": "3243"
    },
    {
        "Subreddit": "r/TimePrincess",
        "Community Category": "Gaming",
        "Member Count": "3243"
    },
    {
        "Subreddit": "r/TTOOstock",
        "Community Category": "Business, Economics, and Finance",
        "Member Count": "3243"
    },
    {
        "Subreddit": "r/whatisthisspider",
        "Community Category": "Outdoors and Nature",
        "Member Count": "3243"
    },
    {
        "Subreddit": "r/Adjuncts",
        "Community Category": "Careers",
        "Member Count": "3242"
    },
    {
        "Subreddit": "r/arielpink",
        "Community Category": "Music",
        "Member Count": "3242"
    },
    {
        "Subreddit": "r/dungeonsofdrakkenheim",
        "Community Category": "Tabletop Games",
        "Member Count": "3242"
    },
    {
        "Subreddit": "r/figures",
        "Community Category": "Hobbies",
        "Member Count": "3242"
    },
    {
        "Subreddit": "r/ATLauncher",
        "Community Category": "Gaming",
        "Member Count": "3241"
    },
    {
        "Subreddit": "r/BlackMediaPresents",
        "Community Category": "Music",
        "Member Count": "3241"
    },
    {
        "Subreddit": "r/Celebs_Braless",
        "Community Category": "Mature Themes and Adult Content",
        "Member Count": "3241"
    },
    {
        "Subreddit": "r/gamecheats",
        "Community Category": "Gaming",
        "Member Count": "3241"
    },
    {
        "Subreddit": "r/NomSaying",
        "Community Category": "A place for fake figures of speech and idioms that sometimes make sense.",
        "Member Count": "3241"
    },
    {
        "Subreddit": "r/TheDarkCrystal",
        "Community Category": "A place to come and discuss every facet of The Dark Crystal and its spinoff media.",
        "Member Count": "3241"
    },
    {
        "Subreddit": "r/audiotechnica",
        "Community Category": "Technology",
        "Member Count": "3240"
    },
    {
        "Subreddit": "r/Daww",
        "Community Category": "Animals and Pets",
        "Member Count": "3240"
    },
    {
        "Subreddit": "r/FairbanksClassic",
        "Community Category": "Gaming",
        "Member Count": "3240"
    },
    {
        "Subreddit": "r/gettoknowtheothers",
        "Community Category": "Internet Culture and Memes",
        "Member Count": "3240"
    },
    {
        "Subreddit": "r/GibiASMR",
        "Community Category": "Podcasts and Streamers",
        "Member Count": "3240"
    },
    {
        "Subreddit": "r/P1Harmony",
        "Community Category": "Music",
        "Member Count": "3240"
    },
    {
        "Subreddit": "r/petsorstuffedanimals",
        "Community Category": "Animals and Pets",
        "Member Count": "3240"
    },
    {
        "Subreddit": "r/ScarletHollow",
        "Community Category": "Gaming",
        "Member Count": "3240"
    },
    {
        "Subreddit": "r/The_Librandu_Files",
        "Community Category": "Politics",
        "Member Count": "3240"
    },
    {
        "Subreddit": "r/TrumpHatesTheTroops",
        "Community Category": "Politics",
        "Member Count": "3240"
    },
    {
        "Subreddit": "r/xandrasnark",
        "Community Category": "Celebrity",
        "Member Count": "3240"
    },
    {
        "Subreddit": "r/956singles",
        "Community Category": "Welcome to 956singles",
        "Member Count": "3239"
    },
    {
        "Subreddit": "r/bmfstarz",
        "Community Category": "Television",
        "Member Count": "3239"
    },
    {
        "Subreddit": "r/EVMOS",
        "Community Category": "Crypto",
        "Member Count": "3239"
    },
    {
        "Subreddit": "r/mariiutrerea_01",
        "Community Category": "https://onlyfans.com/mariiutrera_01\n\nNo selling, no MEGAs. I know a lot of shit ya have is old shit. If someone can post new shit that\u2019ll be appreciated though. Enjoy and let\u2019s grow.",
        "Member Count": "3239"
    },
    {
        "Subreddit": "r/newSuns",
        "Community Category": "Fitness and Nutrition",
        "Member Count": "3239"
    },
    {
        "Subreddit": "r/PenelopeMenchacaa",
        "Community Category": "Celebrity",
        "Member Count": "3239"
    },
    {
        "Subreddit": "r/RickiStafford",
        "Community Category": "Subreddit dedicated to Ricki Stafford",
        "Member Count": "3239"
    },
    {
        "Subreddit": "r/silverton",
        "Community Category": "Place",
        "Member Count": "3239"
    },
    {
        "Subreddit": "r/WeightLossSupport",
        "Community Category": "Fitness and Nutrition",
        "Member Count": "3239"
    },
    {
        "Subreddit": "r/Aristotle",
        "Community Category": "Welcome to Aristotle",
        "Member Count": "3238"
    },
    {
        "Subreddit": "r/AvitalCohen",
        "Community Category": "Mature Themes and Adult Content",
        "Member Count": "3238"
    },
    {
        "Subreddit": "r/EmperorLemon",
        "Community Category": "Podcasts and Streamers",
        "Member Count": "3238"
    },
    {
        "Subreddit": "r/EndOfTheParTy",
        "Community Category": "Addiction Support",
        "Member Count": "3238"
    },
    {
        "Subreddit": "r/Genshin_Trading",
        "Community Category": "Gaming",
        "Member Count": "3238"
    },
    {
        "Subreddit": "r/gloveandboots",
        "Community Category": "This is a place for Glove and Boots related topics, or anything that makes you happy.  Feel free to make a mess.",
        "Member Count": "3238"
    },
    {
        "Subreddit": "r/terrariamods",
        "Community Category": "Gaming",
        "Member Count": "3238"
    },
    {
        "Subreddit": "r/UnexpectedYoda",
        "Community Category": "Funny/Humor",
        "Member Count": "3238"
    },
    {
        "Subreddit": "r/Bolton",
        "Community Category": "Place",
        "Member Count": "3237"
    }
]