[
    {
        "Subreddit": "r/AsukaWWE",
        "Community Category": "Celebrity",
        "Member Count": "5548"
    },
    {
        "Subreddit": "r/RCD_330",
        "Community Category": "Cars and Motor Vehicles",
        "Member Count": "5548"
    },
    {
        "Subreddit": "r/LynetteMains",
        "Community Category": "Gaming",
        "Member Count": "5547"
    },
    {
        "Subreddit": "r/StarWarsArt",
        "Community Category": "Art",
        "Member Count": "5547"
    },
    {
        "Subreddit": "r/IDontWorkHere",
        "Community Category": "Careers",
        "Member Count": "5546"
    },
    {
        "Subreddit": "r/policescanner",
        "Community Category": "Hobbies",
        "Member Count": "5546"
    },
    {
        "Subreddit": "r/QredoNetwork_Official",
        "Community Category": "Deep Tech | DeFi Infrastructure | Instant Cross-Chain Settlement | Empowering Traders & Asset Managers Learn more: http://t.me/QredoNetwork",
        "Member Count": "5546"
    },
    {
        "Subreddit": "r/Alexisonfire",
        "Community Category": "Music",
        "Member Count": "5543"
    },
    {
        "Subreddit": "r/DinosaursMTG",
        "Community Category": "Tabletop Games",
        "Member Count": "5543"
    },
    {
        "Subreddit": "r/Lolboosting",
        "Community Category": "Gaming",
        "Member Count": "5543"
    },
    {
        "Subreddit": "r/osumania",
        "Community Category": "Gaming",
        "Member Count": "5543"
    },
    {
        "Subreddit": "r/SleepTokenTheory",
        "Community Category": "Music",
        "Member Count": "5543"
    },
    {
        "Subreddit": "r/mccisland",
        "Community Category": "Gaming",
        "Member Count": "5542"
    },
    {
        "Subreddit": "r/ArkansasPawgLovers",
        "Community Category": "Mature Themes and Adult Content",
        "Member Count": "5541"
    },
    {
        "Subreddit": "r/Crystalsforbeginners",
        "Community Category": "This is a community to help each other learn more about crystal healing, crystal identifications and working with crystals. Everyone is welcome!",
        "Member Count": "5541"
    },
    {
        "Subreddit": "r/LoveAfterDivorce",
        "Community Category": "Television",
        "Member Count": "5541"
    },
    {
        "Subreddit": "r/monogame",
        "Community Category": "Programming",
        "Member Count": "5541"
    },
    {
        "Subreddit": "r/MilitaryWives",
        "Community Category": "Family and Relationships",
        "Member Count": "5540"
    },
    {
        "Subreddit": "r/PoojaHegde",
        "Community Category": "Celebrity",
        "Member Count": "5540"
    },
    {
        "Subreddit": "r/darkerdungeons5e",
        "Community Category": "Tabletop Games",
        "Member Count": "5539"
    },
    {
        "Subreddit": "r/1001AlbumsGenerator",
        "Community Category": "Music",
        "Member Count": "5538"
    },
    {
        "Subreddit": "r/explainlikedonald",
        "Community Category": "Funny/Humor",
        "Member Count": "5538"
    },
    {
        "Subreddit": "r/omadketo",
        "Community Category": "Fitness and Nutrition",
        "Member Count": "5538"
    },
    {
        "Subreddit": "r/Utilitarianism",
        "Community Category": "Activism",
        "Member Count": "5538"
    },
    {
        "Subreddit": "r/BulletBarry",
        "Community Category": "Podcasts and Streamers",
        "Member Count": "5537"
    },
    {
        "Subreddit": "r/TodoMomo",
        "Community Category": "Anime",
        "Member Count": "5537"
    },
    {
        "Subreddit": "r/GoogleAdwords",
        "Community Category": "Technology",
        "Member Count": "5536"
    },
    {
        "Subreddit": "r/NetflixAustralia",
        "Community Category": "Television",
        "Member Count": "5536"
    },
    {
        "Subreddit": "r/ACInfinityAdvancegrow",
        "Community Category": "Home and Garden",
        "Member Count": "5535"
    },
    {
        "Subreddit": "r/destiel",
        "Community Category": "Television",
        "Member Count": "5535"
    },
    {
        "Subreddit": "r/DiecastCustoms",
        "Community Category": "Hobbies",
        "Member Count": "5535"
    },
    {
        "Subreddit": "r/Islamic_Coin_Official",
        "Community Category": "Crypto",
        "Member Count": "5535"
    },
    {
        "Subreddit": "r/SaudiForSaudis",
        "Community Category": "Place",
        "Member Count": "5535"
    },
    {
        "Subreddit": "r/NFSUnboundGame",
        "Community Category": "Gaming",
        "Member Count": "5534"
    },
    {
        "Subreddit": "r/BuffyverseBabes",
        "Community Category": "Mature Themes and Adult Content",
        "Member Count": "5533"
    },
    {
        "Subreddit": "r/programminghelp",
        "Community Category": "Programming",
        "Member Count": "5533"
    },
    {
        "Subreddit": "r/wholesomejokes",
        "Community Category": "Welcome to wholesomejokes",
        "Member Count": "5533"
    },
    {
        "Subreddit": "r/century",
        "Community Category": "Gaming",
        "Member Count": "5532"
    },
    {
        "Subreddit": "r/RollerChampions",
        "Community Category": "Gaming",
        "Member Count": "5532"
    },
    {
        "Subreddit": "r/ScottishHistory",
        "Community Category": "History",
        "Member Count": "5532"
    },
    {
        "Subreddit": "r/StonkFeed",
        "Community Category": "Business, Economics, and Finance",
        "Member Count": "5532"
    },
    {
        "Subreddit": "r/swgtecosystem",
        "Community Category": "Crypto",
        "Member Count": "5531"
    },
    {
        "Subreddit": "r/HylianWarCrimes",
        "Community Category": "Gaming",
        "Member Count": "5530"
    },
    {
        "Subreddit": "r/SchwinnIC4_BowflexC6",
        "Community Category": "Fitness and Nutrition",
        "Member Count": "5530"
    },
    {
        "Subreddit": "r/ATribeCalledQuest",
        "Community Category": "Music",
        "Member Count": "5529"
    },
    {
        "Subreddit": "r/CFBrevamped",
        "Community Category": "Gaming",
        "Member Count": "5529"
    },
    {
        "Subreddit": "r/EuropeMeta",
        "Community Category": "Place",
        "Member Count": "5529"
    },
    {
        "Subreddit": "r/LibJerk",
        "Community Category": "Politics",
        "Member Count": "5529"
    },
    {
        "Subreddit": "r/nosuchthingasafish",
        "Community Category": "Podcasts and Streamers",
        "Member Count": "5529"
    },
    {
        "Subreddit": "r/buffgame",
        "Community Category": "The official subreddit of BUFF, an app designed by gamers for gamers, a loyalty program that rewards you simply for playing.",
        "Member Count": "5528"
    },
    {
        "Subreddit": "r/CanadaStocks",
        "Community Category": "Business, Economics, and Finance",
        "Member Count": "5528"
    },
    {
        "Subreddit": "r/virginients",
        "Community Category": "Hobbies",
        "Member Count": "5528"
    },
    {
        "Subreddit": "r/Roxy",
        "Community Category": "Anime",
        "Member Count": "5527"
    },
    {
        "Subreddit": "r/BritPop",
        "Community Category": "Music",
        "Member Count": "5526"
    },
    {
        "Subreddit": "r/brutalRejection",
        "Community Category": "Funny/Humor",
        "Member Count": "5526"
    },
    {
        "Subreddit": "r/instagirllove",
        "Community Category": "Mature Themes and Adult Content",
        "Member Count": "5526"
    },
    {
        "Subreddit": "r/MGPMPPJWFA",
        "Community Category": "Music",
        "Member Count": "5526"
    },
    {
        "Subreddit": "r/UK_babes_underrated",
        "Community Category": "Celebrity",
        "Member Count": "5526"
    },
    {
        "Subreddit": "r/d3js",
        "Community Category": "Programming",
        "Member Count": "5525"
    },
    {
        "Subreddit": "r/DirtRacing",
        "Community Category": "Sports",
        "Member Count": "5525"
    },
    {
        "Subreddit": "r/Rotaries",
        "Community Category": "Cars and Motor Vehicles",
        "Member Count": "5525"
    },
    {
        "Subreddit": "r/WinterPark",
        "Community Category": "Place",
        "Member Count": "5524"
    },
    {
        "Subreddit": "r/handpan",
        "Community Category": "Music",
        "Member Count": "5522"
    },
    {
        "Subreddit": "r/myweatherstation",
        "Community Category": "Technology",
        "Member Count": "5522"
    },
    {
        "Subreddit": "r/TheaterDays",
        "Community Category": "Gaming",
        "Member Count": "5522"
    },
    {
        "Subreddit": "r/Traves",
        "Community Category": "Podcasts and Streamers",
        "Member Count": "5522"
    },
    {
        "Subreddit": "r/bunnyflops",
        "Community Category": "Animals and Pets",
        "Member Count": "5521"
    },
    {
        "Subreddit": "r/CatFacts",
        "Community Category": "Animals and Pets",
        "Member Count": "5521"
    },
    {
        "Subreddit": "r/qinmin123",
        "Community Category": "Fashion",
        "Member Count": "5520"
    },
    {
        "Subreddit": "r/tofino",
        "Community Category": "Place",
        "Member Count": "5520"
    },
    {
        "Subreddit": "r/PopTeamEpic",
        "Community Category": "Anime",
        "Member Count": "5519"
    },
    {
        "Subreddit": "r/Tilburg",
        "Community Category": "Place",
        "Member Count": "5519"
    },
    {
        "Subreddit": "r/cardio",
        "Community Category": "Fitness and Nutrition",
        "Member Count": "5518"
    },
    {
        "Subreddit": "r/International",
        "Community Category": "World News",
        "Member Count": "5518"
    },
    {
        "Subreddit": "r/MostlyHarmlessHiker",
        "Community Category": "This is a community for news about the unidentified hiker known as Denim or Mostly Harmless who was found dead in Florida.",
        "Member Count": "5518"
    },
    {
        "Subreddit": "r/EnterpriseArchitect",
        "Community Category": "Careers",
        "Member Count": "5517"
    },
    {
        "Subreddit": "r/FranciaRaisa",
        "Community Category": "Mature Themes and Adult Content",
        "Member Count": "5517"
    },
    {
        "Subreddit": "r/OpenSourceEcology",
        "Community Category": "Open Source Ecology is Network of Farmers, Engineers, and Supporters Building the Global Village Construction Set.\n\nThe Global Village Construction Set (GVCS) is a modular, DIY, low-cost, high-performance platform that allows for the easy fabrication of the 50 different Industrial Machines that it takes to build a small, sustainable civilization with modern comforts.",
        "Member Count": "5517"
    },
    {
        "Subreddit": "r/optimization",
        "Community Category": "Programming",
        "Member Count": "5517"
    },
    {
        "Subreddit": "r/Quadrants",
        "Community Category": "These pictures come in four split colors.",
        "Member Count": "5517"
    },
    {
        "Subreddit": "r/LLMDevs",
        "Community Category": "Technology",
        "Member Count": "5516"
    },
    {
        "Subreddit": "r/BJJWomen",
        "Community Category": "Sports",
        "Member Count": "5515"
    },
    {
        "Subreddit": "r/BT_APC",
        "Community Category": "Mature Themes and Adult Content",
        "Member Count": "5515"
    },
    {
        "Subreddit": "r/worldwidetrans",
        "Community Category": "Mature Themes and Adult Content",
        "Member Count": "5515"
    },
    {
        "Subreddit": "r/absentgrandparents",
        "Community Category": "Family and Relationships",
        "Member Count": "5514"
    },
    {
        "Subreddit": "r/Digihentai",
        "Community Category": "Mature Themes and Adult Content",
        "Member Count": "5514"
    },
    {
        "Subreddit": "r/unexpectedsteamedhams",
        "Community Category": "Internet Culture and Memes",
        "Member Count": "5514"
    },
    {
        "Subreddit": "r/DashieXP",
        "Community Category": "Anything and everything related to Dashie.",
        "Member Count": "5513"
    },
    {
        "Subreddit": "r/Medicaid",
        "Community Category": "Business, Economics, and Finance",
        "Member Count": "5513"
    },
    {
        "Subreddit": "r/AnthropologyMemes",
        "Community Category": "Internet Culture and Memes",
        "Member Count": "5512"
    },
    {
        "Subreddit": "r/ArtConservation",
        "Community Category": "Art",
        "Member Count": "5512"
    },
    {
        "Subreddit": "r/ChurchOfIshigami",
        "Community Category": "Anime",
        "Member Count": "5512"
    },
    {
        "Subreddit": "r/comicreadingorders",
        "Community Category": "Reading, Writing, and Literature",
        "Member Count": "5512"
    },
    {
        "Subreddit": "r/KSIolajidebt",
        "Community Category": "Internet Culture and Memes",
        "Member Count": "5512"
    },
    {
        "Subreddit": "r/Artillery3D",
        "Community Category": "Technology",
        "Member Count": "5511"
    },
    {
        "Subreddit": "r/DueloDeFamosinhas",
        "Community Category": "Mature Themes and Adult Content",
        "Member Count": "5511"
    },
    {
        "Subreddit": "r/EthosGrowery",
        "Community Category": "Mature Themes and Adult Content",
        "Member Count": "5511"
    },
    {
        "Subreddit": "r/MT09",
        "Community Category": "Cars and Motor Vehicles",
        "Member Count": "5511"
    },
    {
        "Subreddit": "r/OfficialKonstantin",
        "Community Category": "Anything about the Youtuber & Camera man Konstantin!",
        "Member Count": "5511"
    },
    {
        "Subreddit": "r/RandomActsofHappyMail",
        "Community Category": "Crafts and DIY",
        "Member Count": "5511"
    },
    {
        "Subreddit": "r/HistoricalFencing",
        "Community Category": "History",
        "Member Count": "5510"
    },
    {
        "Subreddit": "r/birdsnamedfood",
        "Community Category": "Animals and Pets",
        "Member Count": "5509"
    },
    {
        "Subreddit": "r/HDR",
        "Community Category": "Technology",
        "Member Count": "5509"
    },
    {
        "Subreddit": "r/LongBeachIsland",
        "Community Category": "Place",
        "Member Count": "5508"
    },
    {
        "Subreddit": "r/DarkSoulsTheBoardGame",
        "Community Category": "Tabletop Games",
        "Member Count": "5506"
    },
    {
        "Subreddit": "r/remotepython",
        "Community Category": "Careers",
        "Member Count": "5506"
    },
    {
        "Subreddit": "r/OGmololo180",
        "Community Category": "Mature Themes and Adult Content",
        "Member Count": "5505"
    },
    {
        "Subreddit": "r/RepVirgins",
        "Community Category": "Fashion",
        "Member Count": "5505"
    },
    {
        "Subreddit": "r/MovingToUSA",
        "Community Category": "For as long as I can remember I wanted to move to the us. As anyone who has even attempted to understand the tons of requirements (most of whom are not even clear) can tell you it's a pretty difficult task. This is what this sub is for: people to share their experiences with moving to the us as well as tips both for moving to the us as well as what to do after getting there.",
        "Member Count": "5504"
    },
    {
        "Subreddit": "r/Perfusion",
        "Community Category": "Careers",
        "Member Count": "5504"
    },
    {
        "Subreddit": "r/TwoFacedCats",
        "Community Category": "A subreddit for cats with fur patterns/markings that make them appear to have two faces.",
        "Member Count": "5504"
    },
    {
        "Subreddit": "r/UberHaxorNova",
        "Community Category": "Podcasts and Streamers",
        "Member Count": "5504"
    },
    {
        "Subreddit": "r/XenobladeChronicles3",
        "Community Category": "Gaming",
        "Member Count": "5503"
    },
    {
        "Subreddit": "r/madebygoogle",
        "Community Category": "Technology",
        "Member Count": "5502"
    },
    {
        "Subreddit": "r/NewForest",
        "Community Category": "Outdoors and Nature",
        "Member Count": "5502"
    },
    {
        "Subreddit": "r/OceanCityNewJersey",
        "Community Category": "Place",
        "Member Count": "5502"
    },
    {
        "Subreddit": "r/Tdarr",
        "Community Category": "Technology",
        "Member Count": "5502"
    },
    {
        "Subreddit": "r/CroatiaPics",
        "Community Category": "Outdoors and Nature",
        "Member Count": "5501"
    },
    {
        "Subreddit": "r/TheoryofFearMe",
        "Community Category": "Art",
        "Member Count": "5501"
    },
    {
        "Subreddit": "r/linuxprojects",
        "Community Category": "Technology",
        "Member Count": "5500"
    },
    {
        "Subreddit": "r/LuxuryRepsBags",
        "Community Category": "LuxuryRepsBags is Discussion about replica Luxury Designer bags,clothes,shoes,Accessories.this subreddit was formed is hopes of creating a community where we can all enjoy fashion at any level. Buyer: share our experience, reviews , likes, dislikes, everything here!!!",
        "Member Count": "5500"
    },
    {
        "Subreddit": "r/PokemonJessieRule34",
        "Community Category": "Nsfw content of Jessie from team rocket, because she is hot and deserves her own subreddit.",
        "Member Count": "5500"
    },
    {
        "Subreddit": "r/Bittboy",
        "Community Category": "Gaming",
        "Member Count": "5499"
    },
    {
        "Subreddit": "r/centralcoast",
        "Community Category": "Place",
        "Member Count": "5499"
    },
    {
        "Subreddit": "r/diycnc",
        "Community Category": "Crafts and DIY",
        "Member Count": "5499"
    },
    {
        "Subreddit": "r/FrugalWrist",
        "Community Category": "Marketplace and Deals",
        "Member Count": "5499"
    },
    {
        "Subreddit": "r/northernontario",
        "Community Category": "Place",
        "Member Count": "5499"
    },
    {
        "Subreddit": "r/UndertheOakTree",
        "Community Category": "Anime",
        "Member Count": "5499"
    },
    {
        "Subreddit": "r/UnitarianUniversalist",
        "Community Category": "Religion and Spirituality",
        "Member Count": "5499"
    },
    {
        "Subreddit": "r/GetOutOfFrame",
        "Community Category": "Funny/Humor",
        "Member Count": "5498"
    },
    {
        "Subreddit": "r/GSAT",
        "Community Category": "Business, Economics, and Finance",
        "Member Count": "5498"
    },
    {
        "Subreddit": "r/kriyayoga",
        "Community Category": "Fitness and Nutrition",
        "Member Count": "5498"
    },
    {
        "Subreddit": "r/TikTokAdmirer",
        "Community Category": "Mature Themes and Adult Content",
        "Member Count": "5498"
    },
    {
        "Subreddit": "r/WLS_Food",
        "Community Category": "Food and Drink",
        "Member Count": "5498"
    },
    {
        "Subreddit": "r/cityofmist",
        "Community Category": "Tabletop Games",
        "Member Count": "5497"
    },
    {
        "Subreddit": "r/Geometry",
        "Community Category": "Learning and Education",
        "Member Count": "5497"
    },
    {
        "Subreddit": "r/LibraryScience",
        "Community Category": "Careers",
        "Member Count": "5497"
    },
    {
        "Subreddit": "r/mandalas",
        "Community Category": "Religion and Spirituality",
        "Member Count": "5497"
    },
    {
        "Subreddit": "r/ROCents",
        "Community Category": "Mature Themes and Adult Content",
        "Member Count": "5497"
    },
    {
        "Subreddit": "r/TomboyFashionAdvice",
        "Community Category": "Fashion",
        "Member Count": "5497"
    },
    {
        "Subreddit": "r/vrouwvolk",
        "Community Category": "Women's Health",
        "Member Count": "5497"
    },
    {
        "Subreddit": "r/Ecoflow_community",
        "Community Category": "Technology",
        "Member Count": "5496"
    },
    {
        "Subreddit": "r/CraftDocs",
        "Community Category": "Technology",
        "Member Count": "5495"
    },
    {
        "Subreddit": "r/REU",
        "Community Category": "Learning and Education",
        "Member Count": "5495"
    },
    {
        "Subreddit": "r/SurfPunk",
        "Community Category": "Music",
        "Member Count": "5495"
    },
    {
        "Subreddit": "r/Vlogs",
        "Community Category": "Podcasts and Streamers",
        "Member Count": "5495"
    },
    {
        "Subreddit": "r/YoutubeSelfPromotions",
        "Community Category": "Internet Culture and Memes",
        "Member Count": "5495"
    },
    {
        "Subreddit": "r/Awakening",
        "Community Category": "Religion and Spirituality",
        "Member Count": "5494"
    },
    {
        "Subreddit": "r/GreenLattice",
        "Community Category": "Meta/Reddit",
        "Member Count": "5494"
    },
    {
        "Subreddit": "r/whatdoIdo",
        "Community Category": "Family and Relationships",
        "Member Count": "5494"
    },
    {
        "Subreddit": "r/TheBrightSide",
        "Community Category": "The world is a terrible place, full of hatred, violence, and catastrophe. These are the laws of the land..... Or so we are led to believe. \n\nWhat if the world could be pushed forward by good news? News of success, technological advancement, merits of peace, and promoting good will and love amongst our species?\n\nCome in and tell us what you've gleaned from the bright side of human existence.",
        "Member Count": "5493"
    },
    {
        "Subreddit": "r/YodayoAI",
        "Community Category": "Technology",
        "Member Count": "5493"
    },
    {
        "Subreddit": "r/JamesBlake",
        "Community Category": "Music",
        "Member Count": "5492"
    },
    {
        "Subreddit": "r/Jinjer",
        "Community Category": "Music",
        "Member Count": "5492"
    },
    {
        "Subreddit": "r/SeaJobs",
        "Community Category": "Careers",
        "Member Count": "5492"
    },
    {
        "Subreddit": "r/AmIOverreacting",
        "Community Category": "Ethics and Philosophy",
        "Member Count": "5491"
    },
    {
        "Subreddit": "r/AstonMartinFormula1",
        "Community Category": "Sports",
        "Member Count": "5491"
    },
    {
        "Subreddit": "r/dr650",
        "Community Category": "Cars and Motor Vehicles",
        "Member Count": "5491"
    },
    {
        "Subreddit": "r/lesmiserables",
        "Community Category": "Art",
        "Member Count": "5490"
    },
    {
        "Subreddit": "r/PokemonBDSPTrades",
        "Community Category": "Gaming",
        "Member Count": "5490"
    },
    {
        "Subreddit": "r/RZR",
        "Community Category": "Cars and Motor Vehicles",
        "Member Count": "5490"
    },
    {
        "Subreddit": "r/YorForger",
        "Community Category": "Anime",
        "Member Count": "5490"
    },
    {
        "Subreddit": "r/BISMUTH",
        "Community Category": "Crafts and DIY",
        "Member Count": "5489"
    },
    {
        "Subreddit": "r/F1MultiViewer",
        "Community Category": "Television",
        "Member Count": "5489"
    },
    {
        "Subreddit": "r/SFlist",
        "Community Category": "Marketplace and Deals",
        "Member Count": "5489"
    },
    {
        "Subreddit": "r/deepfriedmemespart2",
        "Community Category": "Funny/Humor",
        "Member Count": "5488"
    },
    {
        "Subreddit": "r/oldschoolfantasy",
        "Community Category": "Art",
        "Member Count": "5488"
    },
    {
        "Subreddit": "r/weaponsystems",
        "Community Category": "Military",
        "Member Count": "5488"
    },
    {
        "Subreddit": "r/comp_chem",
        "Community Category": "Science",
        "Member Count": "5487"
    },
    {
        "Subreddit": "r/InvasionAppleTV",
        "Community Category": "Television",
        "Member Count": "5487"
    },
    {
        "Subreddit": "r/kilt",
        "Community Category": "Fashion",
        "Member Count": "5487"
    },
    {
        "Subreddit": "r/swordartonlinememes",
        "Community Category": "Anime",
        "Member Count": "5487"
    },
    {
        "Subreddit": "r/AnimalsBeingScared",
        "Community Category": "Animals and Pets",
        "Member Count": "5486"
    },
    {
        "Subreddit": "r/Cloudstream3",
        "Community Category": "Movies",
        "Member Count": "5486"
    },
    {
        "Subreddit": "r/istebrak",
        "Community Category": "Art",
        "Member Count": "5486"
    },
    {
        "Subreddit": "r/Lineage2",
        "Community Category": "Gaming",
        "Member Count": "5486"
    },
    {
        "Subreddit": "r/olivegarden",
        "Community Category": "Food and Drink",
        "Member Count": "5486"
    },
    {
        "Subreddit": "r/penuma",
        "Community Category": "Men's Health",
        "Member Count": "5486"
    },
    {
        "Subreddit": "r/Amine",
        "Community Category": "Music",
        "Member Count": "5485"
    },
    {
        "Subreddit": "r/AnimeShortFilms",
        "Community Category": "Anime",
        "Member Count": "5484"
    },
    {
        "Subreddit": "r/LawnchairLauncher",
        "Community Category": "Technology",
        "Member Count": "5484"
    },
    {
        "Subreddit": "r/AsianFilms",
        "Community Category": "Movies",
        "Member Count": "5483"
    },
    {
        "Subreddit": "r/Behringer",
        "Community Category": "Music",
        "Member Count": "5483"
    },
    {
        "Subreddit": "r/CryptoDirectory",
        "Community Category": "Token releases and ICOs",
        "Member Count": "5483"
    },
    {
        "Subreddit": "r/UKPublicFreakOuts",
        "Community Category": "Funny/Humor",
        "Member Count": "5483"
    },
    {
        "Subreddit": "r/AddieMarie",
        "Community Category": "Celebrity",
        "Member Count": "5482"
    },
    {
        "Subreddit": "r/GothicMetal",
        "Community Category": "Music",
        "Member Count": "5482"
    },
    {
        "Subreddit": "r/kootenays",
        "Community Category": "Place",
        "Member Count": "5482"
    },
    {
        "Subreddit": "r/projectozone3",
        "Community Category": "Gaming",
        "Member Count": "5482"
    },
    {
        "Subreddit": "r/SmartCar",
        "Community Category": "Cars and Motor Vehicles",
        "Member Count": "5482"
    },
    {
        "Subreddit": "r/StupidpolEurope",
        "Community Category": "Politics",
        "Member Count": "5482"
    },
    {
        "Subreddit": "r/towerunite",
        "Community Category": "Gaming",
        "Member Count": "5481"
    },
    {
        "Subreddit": "r/ImaginaryOoo",
        "Community Category": "Art",
        "Member Count": "5480"
    },
    {
        "Subreddit": "r/Lubuntu",
        "Community Category": "Technology",
        "Member Count": "5480"
    },
    {
        "Subreddit": "r/realitytransurfing",
        "Community Category": "Religion and Spirituality",
        "Member Count": "5480"
    },
    {
        "Subreddit": "r/elegoo",
        "Community Category": "Technology",
        "Member Count": "5479"
    },
    {
        "Subreddit": "r/QueenSized",
        "Community Category": "Mature Themes and Adult Content",
        "Member Count": "5479"
    },
    {
        "Subreddit": "r/NilahMains",
        "Community Category": "Gaming",
        "Member Count": "5478"
    },
    {
        "Subreddit": "r/CountingOnFans",
        "Community Category": "Welcome to the Counting On discussion group.",
        "Member Count": "5477"
    },
    {
        "Subreddit": "r/lordstownmotors",
        "Community Category": "Cars and Motor Vehicles",
        "Member Count": "5477"
    },
    {
        "Subreddit": "r/transistor",
        "Community Category": "Gaming",
        "Member Count": "5477"
    },
    {
        "Subreddit": "r/apple2",
        "Community Category": "Technology",
        "Member Count": "5475"
    },
    {
        "Subreddit": "r/loaches",
        "Community Category": "Animals and Pets",
        "Member Count": "5475"
    },
    {
        "Subreddit": "r/psychotherapists",
        "Community Category": "Careers",
        "Member Count": "5475"
    },
    {
        "Subreddit": "r/SculptedLegs",
        "Community Category": "Mature Themes and Adult Content",
        "Member Count": "5475"
    },
    {
        "Subreddit": "r/YaelShelbia",
        "Community Category": "Celebrity",
        "Member Count": "5475"
    },
    {
        "Subreddit": "r/Devilcorp",
        "Community Category": "Business, Economics, and Finance",
        "Member Count": "5474"
    },
    {
        "Subreddit": "r/frcmemes",
        "Community Category": "Technology",
        "Member Count": "5474"
    },
    {
        "Subreddit": "r/pourpelsupport",
        "Community Category": "Support for all colours",
        "Member Count": "5474"
    },
    {
        "Subreddit": "r/speedpaint",
        "Community Category": "Art",
        "Member Count": "5473"
    },
    {
        "Subreddit": "r/bryanaholly",
        "Community Category": "Mature Themes and Adult Content",
        "Member Count": "5472"
    },
    {
        "Subreddit": "r/DetectiveAlreadyDead",
        "Community Category": "Anime",
        "Member Count": "5472"
    },
    {
        "Subreddit": "r/ff14",
        "Community Category": "Gaming",
        "Member Count": "5472"
    },
    {
        "Subreddit": "r/Threedaysgrace",
        "Community Category": "Music",
        "Member Count": "5472"
    },
    {
        "Subreddit": "r/JourneyPS3",
        "Community Category": "Hobbies",
        "Member Count": "5471"
    },
    {
        "Subreddit": "r/LispyBoi",
        "Community Category": "Podcasts and Streamers",
        "Member Count": "5471"
    },
    {
        "Subreddit": "r/SkirkMains",
        "Community Category": "Gaming",
        "Member Count": "5471"
    },
    {
        "Subreddit": "r/LegendofthePhoenix",
        "Community Category": "Gaming",
        "Member Count": "5470"
    },
    {
        "Subreddit": "r/MonsterTamerWorld",
        "Community Category": "Gaming",
        "Member Count": "5470"
    },
    {
        "Subreddit": "r/nulsservice",
        "Community Category": "Crypto",
        "Member Count": "5470"
    },
    {
        "Subreddit": "r/saltstack",
        "Community Category": "Technology",
        "Member Count": "5470"
    },
    {
        "Subreddit": "r/recalbox",
        "Community Category": "Technology",
        "Member Count": "5469"
    },
    {
        "Subreddit": "r/RocketLeagueAnalysis",
        "Community Category": "Gaming",
        "Member Count": "5469"
    },
    {
        "Subreddit": "r/pokemoncrystal",
        "Community Category": "Gaming",
        "Member Count": "5468"
    },
    {
        "Subreddit": "r/safermoon",
        "Community Category": "Crypto",
        "Member Count": "5468"
    },
    {
        "Subreddit": "r/TicwatchOfficial",
        "Community Category": "Technology",
        "Member Count": "5468"
    },
    {
        "Subreddit": "r/vitamins",
        "Community Category": "Medical and Mental Health",
        "Member Count": "5468"
    },
    {
        "Subreddit": "r/YEGDashCam",
        "Community Category": "Cars and Motor Vehicles",
        "Member Count": "5468"
    },
    {
        "Subreddit": "r/YouTubePromo",
        "Community Category": "Podcasts and Streamers",
        "Member Count": "5467"
    },
    {
        "Subreddit": "r/YouTubeCreators",
        "Community Category": "Podcasts and Streamers",
        "Member Count": "5466"
    },
    {
        "Subreddit": "r/melindalindmark",
        "Community Category": "Celebrity",
        "Member Count": "5465"
    },
    {
        "Subreddit": "r/pdfbooks",
        "Community Category": "Reading, Writing, and Literature",
        "Member Count": "5465"
    },
    {
        "Subreddit": "r/KoalaSampler",
        "Community Category": "Music",
        "Member Count": "5464"
    },
    {
        "Subreddit": "r/steamregionaltricks",
        "Community Category": "Gaming",
        "Member Count": "5464"
    },
    {
        "Subreddit": "r/Kodi_Helpers",
        "Community Category": "Technology",
        "Member Count": "5463"
    },
    {
        "Subreddit": "r/lawofassumption",
        "Community Category": "Religion and Spirituality",
        "Member Count": "5463"
    },
    {
        "Subreddit": "r/TurningRed",
        "Community Category": "Movies",
        "Member Count": "5463"
    },
    {
        "Subreddit": "r/AirBrawl",
        "Community Category": "Air Brawl is a fast paced plane game with two main parts, fighting and racing. The main focus of the game is tight and responsive flight controls and game mechanics that reward skillful flying.",
        "Member Count": "5462"
    },
    {
        "Subreddit": "r/OregonHiking",
        "Community Category": "Place",
        "Member Count": "5462"
    },
    {
        "Subreddit": "r/Roballs",
        "Community Category": "Funny/Humor",
        "Member Count": "5462"
    },
    {
        "Subreddit": "r/Sophisticated_Beauty",
        "Community Category": "Celebrity",
        "Member Count": "5462"
    },
    {
        "Subreddit": "r/ICOcryptos",
        "Community Category": "Solely dedicated to crypto ICO's.",
        "Member Count": "5461"
    },
    {
        "Subreddit": "r/APTests2020",
        "Community Category": "Learning and Education",
        "Member Count": "5460"
    },
    {
        "Subreddit": "r/NLST",
        "Community Category": "Business, Economics, and Finance",
        "Member Count": "5460"
    },
    {
        "Subreddit": "r/Nmat",
        "Community Category": "Learning and Education",
        "Member Count": "5460"
    },
    {
        "Subreddit": "r/WhyWomenKill",
        "Community Category": "Television",
        "Member Count": "5460"
    },
    {
        "Subreddit": "r/Mozart",
        "Community Category": "Music",
        "Member Count": "5459"
    },
    {
        "Subreddit": "r/SanJoseFood",
        "Community Category": "Food and Drink",
        "Member Count": "5459"
    },
    {
        "Subreddit": "r/CSPersonalFinance",
        "Community Category": "Business, Economics, and Finance",
        "Member Count": "5458"
    },
    {
        "Subreddit": "r/FNSCAR",
        "Community Category": "Mature Themes and Adult Content",
        "Member Count": "5458"
    }
]